<?xml version="1.0"?>
<?iotk version="1.2.0"?>
<?iotk file_version="1.0"?>
<?iotk binary="F"?>
<?iotk qe_syntax="F"?>
<Root>
  <GEOMETRY_INFO>
    <NUMBER_OF_TYPES type="integer" size="1">
         1
    </NUMBER_OF_TYPES>
    <NUMBER_OF_ATOMS type="integer" size="1">
         2
    </NUMBER_OF_ATOMS>
    <BRAVAIS_LATTICE_INDEX type="integer" size="1">
         7
    </BRAVAIS_LATTICE_INDEX>
    <SPIN_COMPONENTS type="integer" size="1">
         1
    </SPIN_COMPONENTS>
    <CELL_DIMENSIONS type="real" size="6">
 7.141778489984129E+000
 0.000000000000000E+000
 1.417749096279028E+000
 0.000000000000000E+000
 0.000000000000000E+000
 0.000000000000000E+000
    </CELL_DIMENSIONS>
    <AT type="real" size="9" columns="3">
 5.000000000000091E-001 -5.000000000000091E-001  7.088745481395268E-001 
 5.000000000000091E-001  5.000000000000091E-001  7.088745481395268E-001 
-5.000000000000091E-001 -5.000000000000091E-001  7.088745481395268E-001
    </AT>
    <BG type="real" size="9" columns="3">
 9.999999999999817E-001 -9.999999999999817E-001  0.000000000000000E+000 
 0.000000000000000E+000  9.999999999999817E-001  7.053434226299597E-001 
-9.999999999999817E-001  0.000000000000000E+000  7.053434226299597E-001
    </BG>
    <UNIT_CELL_VOLUME_AU type="real" size="1">
 2.582191881249999E+002
    </UNIT_CELL_VOLUME_AU>
    <TYPE_NAME.1 type="character" size="1" len="3">
Si 
    </TYPE_NAME.1>
    <MASS.1 type="real" size="1">
 2.808600000000000E+001
    </MASS.1>
    <ATOM.1 SPECIES="Si " INDEX="1" TAU="0.000000000000000E+000 0.000000000000000E+000 0.000000000000000E+000"/>
    <ATOM.2 SPECIES="Si " INDEX="1" TAU="4.163336342344413E-017 5.000000000000091E-001 3.544372740697634E-001"/>
    <NUMBER_OF_Q type="integer" size="1">
         1
    </NUMBER_OF_Q>
  </GEOMETRY_INFO>
  <DYNAMICAL_MAT_.1>
    <Q_POINT type="real" size="3" columns="3">
 0.000000000000000E+000  0.000000000000000E+000 -7.053434226299597E-001
    </Q_POINT>
    <PHI.1.1 type="complex" size="9">
 2.696534611644614E-001, 0.000000000000000E+000
-4.163336342344337E-017, 0.000000000000000E+000
 2.775557561562891E-017, 0.000000000000000E+000
 1.387778780781446E-017, 0.000000000000000E+000
 2.696534611644613E-001, 0.000000000000000E+000
-3.469446951953614E-017, 0.000000000000000E+000
 2.775557561562891E-017, 0.000000000000000E+000
-3.469446951953614E-017, 0.000000000000000E+000
 3.641525856615070E-001, 0.000000000000000E+000
    </PHI.1.1>
    <PHI.1.2 type="complex" size="9">
 2.408640199697287E-001, 4.648870192947368E-017
 1.387778780781446E-017,-3.399953793596758E-033
 0.000000000000000E+000, 3.968570531701347E-033
-1.387778780781446E-017, 1.255761001258281E-033
-2.408640199697287E-001,-4.648870192947367E-017
 0.000000000000000E+000,-8.857427626327569E-034
 0.000000000000000E+000,-4.390150438724628E-033
-1.018831514039697E-034, 4.819410895456653E-033
-7.186261071960369E-035,-2.198125407433651E-033
    </PHI.1.2>
    <PHI.2.1 type="complex" size="9">
 2.408640199697287E-001,-4.648870192947367E-017
 1.387778780781446E-017,-6.444990896164021E-034
-2.716884037439192E-034,-2.384365463077264E-033
-1.387778780781446E-017, 1.619223361589024E-033
-2.408640199697287E-001, 4.648870192947367E-017
 0.000000000000000E+000, 1.031398682085821E-033
-2.716884037439192E-034,-3.342762341435082E-034
-3.396105046798990E-035, 2.458905481712139E-033
 1.676794250124086E-034, 1.970152351489082E-033
    </PHI.2.1>
    <PHI.2.2 type="complex" size="9">
 2.696534611644614E-001, 0.000000000000000E+000
-4.163336342344337E-017, 0.000000000000000E+000
 2.775557561562891E-017, 0.000000000000000E+000
 1.387778780781446E-017, 0.000000000000000E+000
 2.696534611644613E-001, 0.000000000000000E+000
-3.469446951953614E-017, 0.000000000000000E+000
 2.775557561562891E-017, 0.000000000000000E+000
-3.469446951953614E-017, 0.000000000000000E+000
 3.641525856615070E-001, 0.000000000000000E+000
    </PHI.2.2>
  </DYNAMICAL_MAT_.1>
  <FREQUENCIES_THZ_CMM1>
    <OMEGA.1 type="real" size="2" columns="2">
 3.488844833440238E+000  1.163753370153240E+002
    </OMEGA.1>
    <DISPLACEMENT.1 type="complex" size="6">
 5.370968468370901E-001,-0.000000000000000E+000
-4.599206204527634E-001, 0.000000000000000E+000
-1.429265845702141E-016, 0.000000000000000E+000
-5.370968468370906E-001, 0.000000000000000E+000
-4.599206204527638E-001, 0.000000000000000E+000
 2.640114338184616E-016,-0.000000000000000E+000
    </DISPLACEMENT.1>
    <OMEGA.2 type="real" size="2" columns="2">
 3.488844833440253E+000  1.163753370153245E+002
    </OMEGA.2>
    <DISPLACEMENT.2 type="complex" size="6">
-4.599206204527640E-001, 0.000000000000000E+000
-5.370968468370906E-001, 0.000000000000000E+000
 2.521926430492852E-016, 0.000000000000000E+000
 4.599206204527634E-001, 0.000000000000000E+000
-5.370968468370901E-001, 0.000000000000000E+000
-7.440670682354083E-017, 0.000000000000000E+000
    </DISPLACEMENT.2>
    <OMEGA.3 type="real" size="2" columns="2">
 1.240814145805556E+001  4.138910478546982E+002
    </OMEGA.3>
    <DISPLACEMENT.3 type="complex" size="6">
-6.260548369145253E-016, 0.000000000000000E+000
 2.029645263965504E-016, 0.000000000000000E+000
 7.751379522322935E-018, 0.000000000000000E+000
-2.740130621125963E-016, 0.000000000000000E+000
-4.004313673664054E-017, 0.000000000000000E+000
 1.000000000000000E+000, 0.000000000000000E+000
    </DISPLACEMENT.3>
    <OMEGA.4 type="real" size="2" columns="2">
 1.240814145805557E+001  4.138910478546984E+002
    </OMEGA.4>
    <DISPLACEMENT.4 type="complex" size="6">
 2.427215711166309E-016,-0.000000000000000E+000
 6.134436649014753E-017, 0.000000000000000E+000
-1.000000000000000E+000, 0.000000000000000E+000
 6.312996297354357E-016,-0.000000000000000E+000
-1.931833506644732E-016, 0.000000000000000E+000
 7.751379522323237E-018,-0.000000000000000E+000
    </DISPLACEMENT.4>
    <OMEGA.5 type="real" size="2" columns="2">
 1.469164229684032E+001  4.900604369720441E+002
    </OMEGA.5>
    <DISPLACEMENT.5 type="complex" size="6">
 4.064917010930860E-001, 0.000000000000000E+000
 5.785883657164640E-001, 0.000000000000000E+000
 5.044343735943844E-016, 0.000000000000000E+000
 4.064917010930868E-001, 0.000000000000000E+000
-5.785883657164643E-001, 0.000000000000000E+000
 2.252687247060051E-016, 0.000000000000000E+000
    </DISPLACEMENT.5>
    <OMEGA.6 type="real" size="2" columns="2">
 1.469164229684033E+001  4.900604369720444E+002
    </OMEGA.6>
    <DISPLACEMENT.6 type="complex" size="6">
-5.785883657164641E-001, 0.000000000000000E+000
 4.064917010930864E-001, 0.000000000000000E+000
-3.989531692168324E-016, 0.000000000000000E+000
-5.785883657164641E-001, 0.000000000000000E+000
-4.064917010930866E-001, 0.000000000000000E+000
-6.195494130976203E-016, 0.000000000000000E+000
    </DISPLACEMENT.6>
  </FREQUENCIES_THZ_CMM1>
</Root>

