<?xml version="1.0" encoding="UTF-8"?>
<Root>
  <GEOMETRY_INFO>
    <NUMBER_OF_TYPES>1</NUMBER_OF_TYPES>
    <NUMBER_OF_ATOMS>2</NUMBER_OF_ATOMS>
    <BRAVAIS_LATTICE_INDEX>2</BRAVAIS_LATTICE_INDEX>
    <SPIN_COMPONENTS>1</SPIN_COMPONENTS>
    <CELL_DIMENSIONS>
   1.015000000000000E+01   0.000000000000000E+00   0.000000000000000E+00
   0.000000000000000E+00   0.000000000000000E+00   0.000000000000000E+00
    </CELL_DIMENSIONS>
    <AT>
  -4.999999999999999E-01   0.000000000000000E+00   4.999999999999999E-01
   0.000000000000000E+00   4.999999999999999E-01   4.999999999999999E-01
  -4.999999999999999E-01   4.999999999999999E-01   0.000000000000000E+00
    </AT>
    <BG>
  -1.000000000000000E+00  -1.000000000000000E+00   1.000000000000000E+00
   1.000000000000000E+00   1.000000000000000E+00   1.000000000000000E+00
  -1.000000000000000E+00   1.000000000000000E+00  -1.000000000000000E+00
    </BG>
    <UNIT_CELL_VOLUME_AU>261.41959374999988</UNIT_CELL_VOLUME_AU>
    <TYPE_NAME.1>Si</TYPE_NAME.1>
    <MASS.1>28.085999999999999</MASS.1>
    <ATOM.1 SPECIES="Si" INDEX="1" TAU="0.0000000000000000 0.0000000000000000 0.0000000000000000"/>
    <ATOM.2 SPECIES="Si" INDEX="1" TAU="0.25000000000000000 0.25000000000000000 0.25000000000000000"/>
    <NUMBER_OF_Q>6</NUMBER_OF_Q>
  </GEOMETRY_INFO>
  <DIELECTRIC_PROPERTIES epsil="true" zstar="true" raman="false">
    <EPSILON>
   2.228272540146913E+01  -1.776356839400250E-15  -1.776356839400250E-15
   1.776356839400250E-15   2.228272540146914E+01   1.776356839400250E-15
   3.552713678800501E-15   8.881784197001252E-15   2.228272540146914E+01
    </EPSILON>
    <ZSTAR>
      <Z_AT_.1>
  -2.442490654175344E-15  -1.998401444325282E-15  -6.661338147750939E-16
  -1.776356839400250E-15  -2.442490654175344E-15   1.332267629550188E-15
  -6.661338147750939E-16   6.661338147750937E-16  -1.998401444325282E-15
      </Z_AT_.1>
      <Z_AT_.2>
   2.664535259100376E-15   1.998401444325282E-15   6.661338147750939E-16
   1.776356839400250E-15   2.664535259100376E-15  -1.332267629550188E-15
   6.661338147750939E-16  -6.661338147750937E-16   1.998401444325282E-15
      </Z_AT_.2>
    </ZSTAR>
  </DIELECTRIC_PROPERTIES>
  <INTERATOMIC_FORCE_CONSTANTS>
    <MESH_NQ1_NQ2_NQ3>
                 4                 4                 4
    </MESH_NQ1_NQ2_NQ3>
    <s_s1_m1_m2_m3.1.1.1.1.1>
      <IFC>
   2.848229995399654E-01  -9.757819552369540E-19   1.626303258728257E-19
  -9.757819552369540E-19   2.848229995399654E-01  -2.710505431213761E-18
   1.626303258728257E-19  -2.710505431213761E-18   2.848229995399654E-01
      </IFC>
    </s_s1_m1_m2_m3.1.1.1.1.1>
    <s_s1_m1_m2_m3.1.1.2.1.1>
      <IFC>
  -3.742641877241898E-03  -1.862497946339836E-03   4.479053795943341E-03
   1.862497946339841E-03   1.059986195261797E-02  -1.862497946339837E-03
   4.479053795943341E-03   1.862497946339840E-03  -3.742641877241899E-03
      </IFC>
    </s_s1_m1_m2_m3.1.1.2.1.1>
    <s_s1_m1_m2_m3.1.1.3.1.1>
      <IFC>
  -2.939277549420666E-05  -1.057097118173367E-18   5.039471004495797E-04
  -1.057097118173367E-18   4.088223787532454E-03  -5.800481622797449E-18
   5.039471004495797E-04  -5.800481622797449E-18  -2.939277549421013E-05
      </IFC>
    </s_s1_m1_m2_m3.1.1.3.1.1>
    <s_s1_m1_m2_m3.1.1.4.1.1>
      <IFC>
  -3.742641877241898E-03   1.862497946339841E-03   4.479053795943341E-03
  -1.862497946339836E-03   1.059986195261797E-02   1.862497946339840E-03
   4.479053795943341E-03  -1.862497946339837E-03  -3.742641877241899E-03
      </IFC>
    </s_s1_m1_m2_m3.1.1.4.1.1>
    <s_s1_m1_m2_m3.1.1.1.2.1>
      <IFC>
   1.059986195261797E-02   1.862497946339836E-03   1.862497946339838E-03
  -1.862497946339841E-03  -3.742641877241902E-03  -4.479053795943344E-03
  -1.862497946339839E-03  -4.479053795943344E-03  -3.742641877241902E-03
      </IFC>
    </s_s1_m1_m2_m3.1.1.1.2.1>
    <s_s1_m1_m2_m3.1.1.2.2.1>
      <IFC>
  -4.203739861952964E-04  -4.780808197830953E-04   3.519910384011418E-04
  -4.780808197830953E-04  -4.203739861952981E-04  -3.519910384011433E-04
   4.856894729035838E-04  -4.856894729035849E-04  -3.163771518603711E-04
      </IFC>
    </s_s1_m1_m2_m3.1.1.2.2.1>
    <s_s1_m1_m2_m3.1.1.3.2.1>
      <IFC>
  -3.163771518603711E-04  -4.856894729035858E-04   4.856894729035830E-04
  -3.519910384011442E-04  -4.203739861953007E-04  -4.780808197830947E-04
   3.519910384011409E-04  -4.780808197830947E-04  -4.203739861953076E-04
      </IFC>
    </s_s1_m1_m2_m3.1.1.3.2.1>
    <s_s1_m1_m2_m3.1.1.4.2.1>
      <IFC>
  -3.742641877241901E-03  -4.479053795943347E-03  -1.862497946339842E-03
  -4.479053795943347E-03  -3.742641877241903E-03  -1.862497946339836E-03
   1.862497946339834E-03   1.862497946339841E-03   1.059986195261797E-02
      </IFC>
    </s_s1_m1_m2_m3.1.1.4.2.1>
    <s_s1_m1_m2_m3.1.1.1.3.1>
      <IFC>
   4.088223787532451E-03   1.897353801849633E-19   2.981555974335137E-18
   1.897353801849633E-19  -2.939277549420666E-05  -5.039471004495830E-04
   2.981555974335137E-18  -5.039471004495830E-04  -2.939277549422054E-05
      </IFC>
    </s_s1_m1_m2_m3.1.1.1.3.1>
    <s_s1_m1_m2_m3.1.1.2.3.1>
      <IFC>
  -4.203739861953068E-04  -3.519910384011454E-04   4.780808197830915E-04
  -4.856894729035869E-04  -3.163771518603729E-04  -4.856894729035861E-04
   4.780808197830913E-04  -3.519910384011446E-04  -4.203739861952946E-04
      </IFC>
    </s_s1_m1_m2_m3.1.1.2.3.1>
    <s_s1_m1_m2_m3.1.1.3.3.1>
      <IFC>
  -2.939277549420666E-05  -5.039471004495847E-04   1.084202172485504E-19
  -5.039471004495847E-04  -2.939277549421013E-05  -4.065758146820642E-18
   1.084202172485504E-19  -4.065758146820642E-18   4.088223787532441E-03
      </IFC>
    </s_s1_m1_m2_m3.1.1.3.3.1>
    <s_s1_m1_m2_m3.1.1.4.3.1>
      <IFC>
  -4.203739861953068E-04  -4.856894729035869E-04   4.780808197830913E-04
  -3.519910384011454E-04  -3.163771518603729E-04  -3.519910384011446E-04
   4.780808197830915E-04  -4.856894729035861E-04  -4.203739861952946E-04
      </IFC>
    </s_s1_m1_m2_m3.1.1.4.3.1>
    <s_s1_m1_m2_m3.1.1.1.4.1>
      <IFC>
   1.059986195261797E-02  -1.862497946339841E-03  -1.862497946339839E-03
   1.862497946339836E-03  -3.742641877241902E-03  -4.479053795943344E-03
   1.862497946339838E-03  -4.479053795943344E-03  -3.742641877241902E-03
      </IFC>
    </s_s1_m1_m2_m3.1.1.1.4.1>
    <s_s1_m1_m2_m3.1.1.2.4.1>
      <IFC>
  -3.742641877241901E-03  -4.479053795943347E-03   1.862497946339834E-03
  -4.479053795943347E-03  -3.742641877241903E-03   1.862497946339841E-03
  -1.862497946339842E-03  -1.862497946339836E-03   1.059986195261797E-02
      </IFC>
    </s_s1_m1_m2_m3.1.1.2.4.1>
    <s_s1_m1_m2_m3.1.1.3.4.1>
      <IFC>
  -3.163771518603711E-04  -3.519910384011442E-04   3.519910384011409E-04
  -4.856894729035858E-04  -4.203739861953007E-04  -4.780808197830947E-04
   4.856894729035830E-04  -4.780808197830947E-04  -4.203739861953076E-04
      </IFC>
    </s_s1_m1_m2_m3.1.1.3.4.1>
    <s_s1_m1_m2_m3.1.1.4.4.1>
      <IFC>
  -4.203739861952964E-04  -4.780808197830953E-04   4.856894729035838E-04
  -4.780808197830953E-04  -4.203739861952981E-04  -4.856894729035849E-04
   3.519910384011418E-04  -3.519910384011433E-04  -3.163771518603711E-04
      </IFC>
    </s_s1_m1_m2_m3.1.1.4.4.1>
    <s_s1_m1_m2_m3.1.1.1.1.2>
      <IFC>
  -3.742641877241909E-03   4.479053795943343E-03  -1.862497946339840E-03
   4.479053795943343E-03  -3.742641877241909E-03   1.862497946339842E-03
   1.862497946339837E-03  -1.862497946339834E-03   1.059986195261797E-02
      </IFC>
    </s_s1_m1_m2_m3.1.1.1.1.2>
    <s_s1_m1_m2_m3.1.1.2.1.2>
      <IFC>
  -3.163771518603694E-04   4.856894729035838E-04   4.856894729035823E-04
   3.519910384011421E-04  -4.203739861952998E-04   4.780808197830961E-04
   3.519910384011404E-04   4.780808197830961E-04  -4.203739861953094E-04
      </IFC>
    </s_s1_m1_m2_m3.1.1.2.1.2>
    <s_s1_m1_m2_m3.1.1.3.1.2>
      <IFC>
  -4.203739861953111E-04   4.780808197830989E-04   3.519910384011417E-04
   4.780808197830989E-04  -4.203739861953111E-04   3.519910384011458E-04
   4.856894729035836E-04   4.856894729035875E-04  -3.163771518603694E-04
      </IFC>
    </s_s1_m1_m2_m3.1.1.3.1.2>
    <s_s1_m1_m2_m3.1.1.4.1.2>
      <IFC>
   1.059986195261797E-02  -1.862497946339840E-03   1.862497946339837E-03
   1.862497946339837E-03  -3.742641877241905E-03   4.479053795943346E-03
  -1.862497946339840E-03   4.479053795943346E-03  -3.742641877241909E-03
      </IFC>
    </s_s1_m1_m2_m3.1.1.4.1.2>
    <s_s1_m1_m2_m3.1.1.1.2.2>
      <IFC>
  -4.203739861953007E-04   3.519910384011452E-04  -4.780808197830987E-04
   4.856894729035870E-04  -3.163771518603711E-04  -4.856894729035804E-04
  -4.780808197830991E-04  -3.519910384011387E-04  -4.203739861953111E-04
      </IFC>
    </s_s1_m1_m2_m3.1.1.1.2.2>
    <s_s1_m1_m2_m3.1.1.2.2.2>
      <IFC>
  -2.578577152540298E-05  -1.951563910473908E-18  -4.607859233063394E-18
  -1.951563910473908E-18  -2.578577152540472E-05   3.632077277826440E-18
  -4.607859233063394E-18   3.632077277826440E-18  -2.578577152539865E-05
      </IFC>
    </s_s1_m1_m2_m3.1.1.2.2.2>
    <s_s1_m1_m2_m3.1.1.3.2.2>
      <IFC>
  -4.203739861953042E-04  -3.519910384011452E-04  -4.780808197830942E-04
  -4.856894729035869E-04  -3.163771518603711E-04   4.856894729035922E-04
  -4.780808197830941E-04   3.519910384011506E-04  -4.203739861953094E-04
      </IFC>
    </s_s1_m1_m2_m3.1.1.3.2.2>
    <s_s1_m1_m2_m3.1.1.4.2.2>
      <IFC>
  -4.094834901518293E-04   2.168404344971009E-19  -3.306816626080789E-18
   2.168404344971009E-19  -4.088760693871565E-04   7.101524229780054E-18
  -3.306816626080789E-18   7.101524229780054E-18  -4.094834901518371E-04
      </IFC>
    </s_s1_m1_m2_m3.1.1.4.2.2>
    <s_s1_m1_m2_m3.1.1.1.3.2>
      <IFC>
  -4.203739861953215E-04   4.780808197830952E-04  -3.519910384011484E-04
   4.780808197830952E-04  -4.203739861953215E-04  -3.519910384011427E-04
  -4.856894729035903E-04  -4.856894729035843E-04  -3.163771518603711E-04
      </IFC>
    </s_s1_m1_m2_m3.1.1.1.3.2>
    <s_s1_m1_m2_m3.1.1.2.3.2>
      <IFC>
  -3.163771518603763E-04  -4.856894729035902E-04  -4.856894729035887E-04
  -3.519910384011486E-04  -4.203739861953068E-04   4.780808197830939E-04
  -3.519910384011467E-04   4.780808197830938E-04  -4.203739861953128E-04
      </IFC>
    </s_s1_m1_m2_m3.1.1.2.3.2>
    <s_s1_m1_m2_m3.1.1.3.3.2>
      <IFC>
  -4.734657425755039E-04  -1.123187092262717E-04  -7.341850851687885E-05
  -1.123187092262716E-04  -4.734657425755039E-04   7.341850851687328E-05
   7.341850851687430E-05  -7.341850851688022E-05  -3.884019074319785E-04
      </IFC>
    </s_s1_m1_m2_m3.1.1.3.3.2>
    <s_s1_m1_m2_m3.1.1.4.3.2>
      <IFC>
  -3.884019074319664E-04  -7.341850851687735E-05   7.341850851687169E-05
   7.341850851687599E-05  -4.734657425754891E-04  -1.123187092262648E-04
  -7.341850851688144E-05  -1.123187092262647E-04  -4.734657425754830E-04
      </IFC>
    </s_s1_m1_m2_m3.1.1.4.3.2>
    <s_s1_m1_m2_m3.1.1.1.4.2>
      <IFC>
  -3.742641877241902E-03   1.862497946339837E-03  -4.479053795943346E-03
  -1.862497946339839E-03   1.059986195261797E-02  -1.862497946339837E-03
  -4.479053795943346E-03   1.862497946339839E-03  -3.742641877241912E-03
      </IFC>
    </s_s1_m1_m2_m3.1.1.1.4.2>
    <s_s1_m1_m2_m3.1.1.2.4.2>
      <IFC>
  -4.088760693871617E-04   6.505213034913027E-19  -8.944667923005412E-18
   6.505213034913027E-19  -4.094834901518310E-04   1.897353801849633E-18
  -8.944667923005412E-18   1.897353801849633E-18  -4.094834901518319E-04
      </IFC>
    </s_s1_m1_m2_m3.1.1.2.4.2>
    <s_s1_m1_m2_m3.1.1.3.4.2>
      <IFC>
  -4.734657425754830E-04   7.341850851687976E-05   1.123187092262637E-04
  -7.341850851687375E-05  -3.884019074319664E-04  -7.341850851687369E-05
   1.123187092262636E-04   7.341850851687976E-05  -4.734657425754882E-04
      </IFC>
    </s_s1_m1_m2_m3.1.1.3.4.2>
    <s_s1_m1_m2_m3.1.1.4.4.2>
      <IFC>
  -4.094834901518362E-04  -6.505213034913027E-19  -6.776263578034403E-18
  -6.505213034913027E-19  -4.094834901518310E-04   4.499439015814843E-18
  -6.776263578034403E-18   4.499439015814843E-18  -4.088760693871556E-04
      </IFC>
    </s_s1_m1_m2_m3.1.1.4.4.2>
    <s_s1_m1_m2_m3.1.1.1.1.3>
      <IFC>
  -2.939277549418584E-05   5.039471004495848E-04   3.089976191583688E-18
   5.039471004495848E-04  -2.939277549418584E-05  -5.421010862427522E-19
   3.089976191583688E-18  -5.421010862427522E-19   4.088223787532486E-03
      </IFC>
    </s_s1_m1_m2_m3.1.1.1.1.3>
    <s_s1_m1_m2_m3.1.1.2.1.3>
      <IFC>
  -4.203739861953033E-04   3.519910384011417E-04   4.780808197830939E-04
   4.856894729035836E-04  -3.163771518603694E-04   4.856894729035849E-04
   4.780808197830944E-04   3.519910384011432E-04  -4.203739861953050E-04
      </IFC>
    </s_s1_m1_m2_m3.1.1.2.1.3>
    <s_s1_m1_m2_m3.1.1.3.1.3>
      <IFC>
   4.088223787532458E-03  -3.171291354520100E-18   4.553649124439119E-18
  -3.171291354520100E-18  -2.939277549420319E-05   5.039471004495836E-04
   4.553649124439119E-18   5.039471004495836E-04  -2.939277549422747E-05
      </IFC>
    </s_s1_m1_m2_m3.1.1.3.1.3>
    <s_s1_m1_m2_m3.1.1.4.1.3>
      <IFC>
  -4.203739861953033E-04   4.856894729035836E-04   4.780808197830944E-04
   3.519910384011417E-04  -3.163771518603694E-04   3.519910384011432E-04
   4.780808197830939E-04   4.856894729035849E-04  -4.203739861953050E-04
      </IFC>
    </s_s1_m1_m2_m3.1.1.4.1.3>
    <s_s1_m1_m2_m3.1.1.1.2.3>
      <IFC>
  -3.163771518603711E-04   4.856894729035829E-04  -4.856894729035874E-04
   3.519910384011413E-04  -4.203739861953007E-04  -4.780808197830970E-04
  -3.519910384011452E-04  -4.780808197830974E-04  -4.203739861953076E-04
      </IFC>
    </s_s1_m1_m2_m3.1.1.1.2.3>
    <s_s1_m1_m2_m3.1.1.2.2.3>
      <IFC>
  -4.203739861952998E-04  -4.780808197831005E-04  -3.519910384011465E-04
  -4.780808197831005E-04  -4.203739861953016E-04   3.519910384011419E-04
  -4.856894729035884E-04   4.856894729035835E-04  -3.163771518603711E-04
      </IFC>
    </s_s1_m1_m2_m3.1.1.2.2.3>
    <s_s1_m1_m2_m3.1.1.3.2.3>
      <IFC>
  -3.884019074319664E-04   7.341850851687347E-05   7.341850851687288E-05
  -7.341850851687998E-05  -4.734657425754865E-04   1.123187092262659E-04
  -7.341850851688033E-05   1.123187092262659E-04  -4.734657425754761E-04
      </IFC>
    </s_s1_m1_m2_m3.1.1.3.2.3>
    <s_s1_m1_m2_m3.1.1.4.2.3>
      <IFC>
  -4.734657425754822E-04   1.123187092262673E-04  -7.341850851688161E-05
   1.123187092262673E-04  -4.734657425754839E-04  -7.341850851687629E-05
   7.341850851687141E-05   7.341850851687705E-05  -3.884019074319508E-04
      </IFC>
    </s_s1_m1_m2_m3.1.1.4.2.3>
    <s_s1_m1_m2_m3.1.1.1.3.3>
      <IFC>
  -2.939277549420666E-05  -1.057097118173367E-18  -5.039471004495836E-04
  -1.057097118173367E-18   4.088223787532451E-03  -4.011548038196366E-18
  -5.039471004495836E-04  -4.011548038196366E-18  -2.939277549422054E-05
      </IFC>
    </s_s1_m1_m2_m3.1.1.1.3.3>
    <s_s1_m1_m2_m3.1.1.2.3.3>
      <IFC>
  -4.734657425754856E-04  -7.341850851687366E-05  -1.123187092262683E-04
   7.341850851687968E-05  -3.884019074319664E-04  -7.341850851687331E-05
  -1.123187092262683E-04   7.341850851687998E-05  -4.734657425754874E-04
      </IFC>
    </s_s1_m1_m2_m3.1.1.2.3.3>
    <s_s1_m1_m2_m3.1.1.3.3.3>
      <IFC>
   3.355867178670008E-04   3.632077277826440E-18  -1.409462824231156E-18
   3.632077277826440E-18   3.355867178670043E-04  -2.710505431213761E-19
  -1.409462824231156E-18  -2.710505431213761E-19   3.355867178669938E-04
      </IFC>
    </s_s1_m1_m2_m3.1.1.3.3.3>
    <s_s1_m1_m2_m3.1.1.4.3.3>
      <IFC>
  -4.734657425754856E-04   7.341850851687968E-05  -1.123187092262683E-04
  -7.341850851687366E-05  -3.884019074319664E-04   7.341850851687998E-05
  -1.123187092262683E-04  -7.341850851687331E-05  -4.734657425754874E-04
      </IFC>
    </s_s1_m1_m2_m3.1.1.4.3.3>
    <s_s1_m1_m2_m3.1.1.1.4.3>
      <IFC>
  -3.163771518603711E-04   3.519910384011413E-04  -3.519910384011452E-04
   4.856894729035829E-04  -4.203739861953007E-04  -4.780808197830974E-04
  -4.856894729035874E-04  -4.780808197830970E-04  -4.203739861953076E-04
      </IFC>
    </s_s1_m1_m2_m3.1.1.1.4.3>
    <s_s1_m1_m2_m3.1.1.2.4.3>
      <IFC>
  -4.734657425754822E-04   1.123187092262673E-04   7.341850851687141E-05
   1.123187092262673E-04  -4.734657425754839E-04   7.341850851687705E-05
  -7.341850851688161E-05  -7.341850851687629E-05  -3.884019074319508E-04
      </IFC>
    </s_s1_m1_m2_m3.1.1.2.4.3>
    <s_s1_m1_m2_m3.1.1.3.4.3>
      <IFC>
  -3.884019074319664E-04  -7.341850851687998E-05  -7.341850851688033E-05
   7.341850851687347E-05  -4.734657425754865E-04   1.123187092262659E-04
   7.341850851687288E-05   1.123187092262659E-04  -4.734657425754761E-04
      </IFC>
    </s_s1_m1_m2_m3.1.1.3.4.3>
    <s_s1_m1_m2_m3.1.1.4.4.3>
      <IFC>
  -4.203739861952998E-04  -4.780808197831005E-04  -4.856894729035884E-04
  -4.780808197831005E-04  -4.203739861953016E-04   4.856894729035835E-04
  -3.519910384011465E-04   3.519910384011419E-04  -3.163771518603711E-04
      </IFC>
    </s_s1_m1_m2_m3.1.1.4.4.3>
    <s_s1_m1_m2_m3.1.1.1.1.4>
      <IFC>
  -3.742641877241909E-03   4.479053795943343E-03   1.862497946339837E-03
   4.479053795943343E-03  -3.742641877241909E-03  -1.862497946339834E-03
  -1.862497946339840E-03   1.862497946339842E-03   1.059986195261797E-02
      </IFC>
    </s_s1_m1_m2_m3.1.1.1.1.4>
    <s_s1_m1_m2_m3.1.1.2.1.4>
      <IFC>
   1.059986195261797E-02   1.862497946339837E-03  -1.862497946339840E-03
  -1.862497946339840E-03  -3.742641877241905E-03   4.479053795943346E-03
   1.862497946339837E-03   4.479053795943346E-03  -3.742641877241909E-03
      </IFC>
    </s_s1_m1_m2_m3.1.1.2.1.4>
    <s_s1_m1_m2_m3.1.1.3.1.4>
      <IFC>
  -4.203739861953111E-04   4.780808197830989E-04   4.856894729035836E-04
   4.780808197830989E-04  -4.203739861953111E-04   4.856894729035875E-04
   3.519910384011417E-04   3.519910384011458E-04  -3.163771518603694E-04
      </IFC>
    </s_s1_m1_m2_m3.1.1.3.1.4>
    <s_s1_m1_m2_m3.1.1.4.1.4>
      <IFC>
  -3.163771518603694E-04   3.519910384011421E-04   3.519910384011404E-04
   4.856894729035838E-04  -4.203739861952998E-04   4.780808197830961E-04
   4.856894729035823E-04   4.780808197830961E-04  -4.203739861953094E-04
      </IFC>
    </s_s1_m1_m2_m3.1.1.4.1.4>
    <s_s1_m1_m2_m3.1.1.1.2.4>
      <IFC>
  -3.742641877241902E-03  -1.862497946339839E-03  -4.479053795943346E-03
   1.862497946339837E-03   1.059986195261797E-02   1.862497946339839E-03
  -4.479053795943346E-03  -1.862497946339837E-03  -3.742641877241912E-03
      </IFC>
    </s_s1_m1_m2_m3.1.1.1.2.4>
    <s_s1_m1_m2_m3.1.1.2.2.4>
      <IFC>
  -4.094834901518362E-04  -6.505213034913027E-19  -6.776263578034403E-18
  -6.505213034913027E-19  -4.094834901518310E-04   4.499439015814843E-18
  -6.776263578034403E-18   4.499439015814843E-18  -4.088760693871556E-04
      </IFC>
    </s_s1_m1_m2_m3.1.1.2.2.4>
    <s_s1_m1_m2_m3.1.1.3.2.4>
      <IFC>
  -4.734657425754830E-04  -7.341850851687375E-05   1.123187092262636E-04
   7.341850851687976E-05  -3.884019074319664E-04   7.341850851687976E-05
   1.123187092262637E-04  -7.341850851687369E-05  -4.734657425754882E-04
      </IFC>
    </s_s1_m1_m2_m3.1.1.3.2.4>
    <s_s1_m1_m2_m3.1.1.4.2.4>
      <IFC>
  -4.088760693871617E-04   6.505213034913027E-19  -8.944667923005412E-18
   6.505213034913027E-19  -4.094834901518310E-04   1.897353801849633E-18
  -8.944667923005412E-18   1.897353801849633E-18  -4.094834901518319E-04
      </IFC>
    </s_s1_m1_m2_m3.1.1.4.2.4>
    <s_s1_m1_m2_m3.1.1.1.3.4>
      <IFC>
  -4.203739861953215E-04   4.780808197830952E-04  -4.856894729035903E-04
   4.780808197830952E-04  -4.203739861953215E-04  -4.856894729035843E-04
  -3.519910384011484E-04  -3.519910384011427E-04  -3.163771518603711E-04
      </IFC>
    </s_s1_m1_m2_m3.1.1.1.3.4>
    <s_s1_m1_m2_m3.1.1.2.3.4>
      <IFC>
  -3.884019074319664E-04   7.341850851687599E-05  -7.341850851688144E-05
  -7.341850851687735E-05  -4.734657425754891E-04  -1.123187092262647E-04
   7.341850851687169E-05  -1.123187092262648E-04  -4.734657425754830E-04
      </IFC>
    </s_s1_m1_m2_m3.1.1.2.3.4>
    <s_s1_m1_m2_m3.1.1.3.3.4>
      <IFC>
  -4.734657425755039E-04  -1.123187092262716E-04   7.341850851687430E-05
  -1.123187092262717E-04  -4.734657425755039E-04  -7.341850851688022E-05
  -7.341850851687885E-05   7.341850851687328E-05  -3.884019074319785E-04
      </IFC>
    </s_s1_m1_m2_m3.1.1.3.3.4>
    <s_s1_m1_m2_m3.1.1.4.3.4>
      <IFC>
  -3.163771518603763E-04  -3.519910384011486E-04  -3.519910384011467E-04
  -4.856894729035902E-04  -4.203739861953068E-04   4.780808197830938E-04
  -4.856894729035887E-04   4.780808197830939E-04  -4.203739861953128E-04
      </IFC>
    </s_s1_m1_m2_m3.1.1.4.3.4>
    <s_s1_m1_m2_m3.1.1.1.4.4>
      <IFC>
  -4.203739861953007E-04   4.856894729035870E-04  -4.780808197830991E-04
   3.519910384011452E-04  -3.163771518603711E-04  -3.519910384011387E-04
  -4.780808197830987E-04  -4.856894729035804E-04  -4.203739861953111E-04
      </IFC>
    </s_s1_m1_m2_m3.1.1.1.4.4>
    <s_s1_m1_m2_m3.1.1.2.4.4>
      <IFC>
  -4.094834901518293E-04   2.168404344971009E-19  -3.306816626080789E-18
   2.168404344971009E-19  -4.088760693871565E-04   7.101524229780054E-18
  -3.306816626080789E-18   7.101524229780054E-18  -4.094834901518371E-04
      </IFC>
    </s_s1_m1_m2_m3.1.1.2.4.4>
    <s_s1_m1_m2_m3.1.1.3.4.4>
      <IFC>
  -4.203739861953042E-04  -4.856894729035869E-04  -4.780808197830941E-04
  -3.519910384011452E-04  -3.163771518603711E-04   3.519910384011506E-04
  -4.780808197830942E-04   4.856894729035922E-04  -4.203739861953094E-04
      </IFC>
    </s_s1_m1_m2_m3.1.1.3.4.4>
    <s_s1_m1_m2_m3.1.1.4.4.4>
      <IFC>
  -2.578577152540298E-05  -1.951563910473908E-18  -4.607859233063394E-18
  -1.951563910473908E-18  -2.578577152540472E-05   3.632077277826440E-18
  -4.607859233063394E-18   3.632077277826440E-18  -2.578577152539865E-05
      </IFC>
    </s_s1_m1_m2_m3.1.1.4.4.4>
    <s_s1_m1_m2_m3.1.2.1.1.1>
      <IFC>
  -7.109230137579478E-02  -4.648977156803537E-02  -4.648977156803537E-02
  -4.648977156803538E-02  -7.109230137579478E-02  -4.648977156803538E-02
  -4.648977156803537E-02  -4.648977156803538E-02  -7.109230137579478E-02
      </IFC>
    </s_s1_m1_m2_m3.1.2.1.1.1>
    <s_s1_m1_m2_m3.1.2.2.1.1>
      <IFC>
   3.797806257029694E-04   8.767585921516952E-04  -8.767585921517011E-04
   8.767585921516958E-04   4.853788793123512E-04   3.565134847530022E-04
  -8.767585921517033E-04   3.565134847530016E-04   4.853788793123561E-04
      </IFC>
    </s_s1_m1_m2_m3.1.2.2.1.1>
    <s_s1_m1_m2_m3.1.2.3.1.1>
      <IFC>
   1.870730363497499E-05   3.627645821839279E-04   1.974951642235757E-05
   3.627645821839285E-04  -5.593567558623649E-05   3.627645821839322E-04
   1.974951642235313E-05   3.627645821839324E-04   1.870730363497542E-05
      </IFC>
    </s_s1_m1_m2_m3.1.2.3.1.1>
    <s_s1_m1_m2_m3.1.2.4.1.1>
      <IFC>
   4.853788793123602E-04   3.565134847530004E-04  -8.767585921516952E-04
   3.565134847530005E-04   4.853788793123565E-04   8.767585921516995E-04
  -8.767585921516972E-04   8.767585921517012E-04   3.797806257029770E-04
      </IFC>
    </s_s1_m1_m2_m3.1.2.4.1.1>
    <s_s1_m1_m2_m3.1.2.1.2.1>
      <IFC>
  -7.109230137579479E-02   4.648977156803537E-02   4.648977156803537E-02
   4.648977156803537E-02  -7.109230137579478E-02  -4.648977156803537E-02
   4.648977156803537E-02  -4.648977156803537E-02  -7.109230137579478E-02
      </IFC>
    </s_s1_m1_m2_m3.1.2.1.2.1>
    <s_s1_m1_m2_m3.1.2.2.2.1>
      <IFC>
  -4.870216683949668E-04  -1.177690720465725E-03   6.445264063880138E-04
  -1.177690720465725E-03  -4.023796425073020E-03   1.177690720465708E-03
   6.445264063880121E-04   1.177690720465707E-03  -4.870216683949668E-04
      </IFC>
    </s_s1_m1_m2_m3.1.2.2.2.1>
    <s_s1_m1_m2_m3.1.2.3.2.1>
      <IFC>
  -4.870216683949613E-04   1.177690720465706E-03   6.445264063880131E-04
   1.177690720465706E-03  -4.023796425073014E-03  -1.177690720465725E-03
   6.445264063880118E-04  -1.177690720465720E-03  -4.870216683949603E-04
      </IFC>
    </s_s1_m1_m2_m3.1.2.3.2.1>
    <s_s1_m1_m2_m3.1.2.4.2.1>
      <IFC>
  -7.109230137579478E-02  -4.648977156803537E-02   4.648977156803537E-02
  -4.648977156803537E-02  -7.109230137579478E-02   4.648977156803538E-02
   4.648977156803537E-02   4.648977156803538E-02  -7.109230137579478E-02
      </IFC>
    </s_s1_m1_m2_m3.1.2.4.2.1>
    <s_s1_m1_m2_m3.1.2.1.3.1>
      <IFC>
  -4.023796425073025E-03  -1.177690720465720E-03  -1.177690720465722E-03
  -1.177690720465722E-03  -4.870216683949772E-04  -6.445264063880034E-04
  -1.177690720465722E-03  -6.445264063880017E-04  -4.870216683949755E-04
      </IFC>
    </s_s1_m1_m2_m3.1.2.1.3.1>
    <s_s1_m1_m2_m3.1.2.2.3.1>
      <IFC>
   7.255340031788692E-04   8.494255506852406E-04  -8.494255506852274E-04
   8.494255506852405E-04   7.255340031788633E-04   8.494255506852431E-04
  -8.494255506852291E-04   8.494255506852429E-04   7.255340031788705E-04
      </IFC>
    </s_s1_m1_m2_m3.1.2.2.3.1>
    <s_s1_m1_m2_m3.1.2.3.3.1>
      <IFC>
  -4.870216683949748E-04  -6.445264063879992E-04  -1.177690720465717E-03
  -6.445264063879995E-04  -4.870216683949801E-04  -1.177690720465717E-03
  -1.177690720465721E-03  -1.177690720465714E-03  -4.023796425073025E-03
      </IFC>
    </s_s1_m1_m2_m3.1.2.3.3.1>
    <s_s1_m1_m2_m3.1.2.4.3.1>
      <IFC>
   4.853788793123576E-04   8.767585921516781E-04  -3.565134847530093E-04
   8.767585921516780E-04   3.797806257029655E-04   8.767585921516791E-04
  -3.565134847530099E-04   8.767585921516800E-04   4.853788793123589E-04
      </IFC>
    </s_s1_m1_m2_m3.1.2.4.3.1>
    <s_s1_m1_m2_m3.1.2.1.4.1>
      <IFC>
  -4.023796425073008E-03   1.177690720465721E-03   1.177690720465711E-03
   1.177690720465721E-03  -4.870216683949523E-04  -6.445264063880189E-04
   1.177690720465710E-03  -6.445264063880199E-04  -4.870216683949566E-04
      </IFC>
    </s_s1_m1_m2_m3.1.2.1.4.1>
    <s_s1_m1_m2_m3.1.2.2.4.1>
      <IFC>
  -4.870216683949616E-04  -6.445264063880130E-04   1.177690720465710E-03
  -6.445264063880140E-04  -4.870216683949629E-04   1.177690720465726E-03
   1.177690720465707E-03   1.177690720465725E-03  -4.023796425073010E-03
      </IFC>
    </s_s1_m1_m2_m3.1.2.2.4.1>
    <s_s1_m1_m2_m3.1.2.3.4.1>
      <IFC>
   1.870730363497314E-05  -1.974951642237115E-05  -3.627645821839132E-04
  -1.974951642237175E-05   1.870730363496854E-05   3.627645821839314E-04
  -3.627645821839156E-04   3.627645821839340E-04  -5.593567558623275E-05
      </IFC>
    </s_s1_m1_m2_m3.1.2.3.4.1>
    <s_s1_m1_m2_m3.1.2.4.4.1>
      <IFC>
  -5.593567558624148E-05   3.627645821839345E-04  -3.627645821839181E-04
   3.627645821839319E-04   1.870730363496415E-05  -1.974951642237134E-05
  -3.627645821839198E-04  -1.974951642237047E-05   1.870730363497282E-05
      </IFC>
    </s_s1_m1_m2_m3.1.2.4.4.1>
    <s_s1_m1_m2_m3.1.2.1.1.2>
      <IFC>
   3.797806257029631E-04  -8.767585921516988E-04   8.767585921516884E-04
  -8.767585921516980E-04   4.853788793123476E-04   3.565134847530070E-04
   8.767585921516854E-04   3.565134847530083E-04   4.853788793123554E-04
      </IFC>
    </s_s1_m1_m2_m3.1.2.1.1.2>
    <s_s1_m1_m2_m3.1.2.2.1.2>
      <IFC>
   3.385018625113989E-04  -1.772265613279718E-04  -1.772265613279663E-04
  -1.772265613279715E-04   3.567031013005624E-04   1.453098128035644E-04
  -1.772265613279672E-04   1.453098128035643E-04   3.567031013005619E-04
      </IFC>
    </s_s1_m1_m2_m3.1.2.2.1.2>
    <s_s1_m1_m2_m3.1.2.3.1.2>
      <IFC>
   3.567031013005572E-04   1.453098128035627E-04  -1.772265613279641E-04
   1.453098128035633E-04   3.567031013005585E-04  -1.772265613279732E-04
  -1.772265613279663E-04  -1.772265613279732E-04   3.385018625113984E-04
      </IFC>
    </s_s1_m1_m2_m3.1.2.3.1.2>
    <s_s1_m1_m2_m3.1.2.4.1.2>
      <IFC>
   4.853788793123657E-04   3.565134847530069E-04   8.767585921516914E-04
   3.565134847530071E-04   4.853788793123637E-04  -8.767585921517008E-04
   8.767585921516920E-04  -8.767585921517017E-04   3.797806257029762E-04
      </IFC>
    </s_s1_m1_m2_m3.1.2.4.1.2>
    <s_s1_m1_m2_m3.1.2.1.2.2>
      <IFC>
  -4.870216683949824E-04   6.445264063880164E-04  -1.177690720465724E-03
   6.445264063880164E-04  -4.870216683949616E-04   1.177690720465707E-03
  -1.177690720465724E-03   1.177690720465710E-03  -4.023796425073022E-03
      </IFC>
    </s_s1_m1_m2_m3.1.2.1.2.2>
    <s_s1_m1_m2_m3.1.2.2.2.2>
      <IFC>
   7.255340031788853E-04  -8.494255506852390E-04  -8.494255506852484E-04
  -8.494255506852393E-04   7.255340031788852E-04  -8.494255506852363E-04
  -8.494255506852481E-04  -8.494255506852358E-04   7.255340031788876E-04
      </IFC>
    </s_s1_m1_m2_m3.1.2.2.2.2>
    <s_s1_m1_m2_m3.1.2.3.2.2>
      <IFC>
  -4.023796425073019E-03   1.177690720465700E-03  -1.177690720465723E-03
   1.177690720465702E-03  -4.870216683949691E-04   6.445264063880146E-04
  -1.177690720465724E-03   6.445264063880152E-04  -4.870216683949645E-04
      </IFC>
    </s_s1_m1_m2_m3.1.2.3.2.2>
    <s_s1_m1_m2_m3.1.2.4.2.2>
      <IFC>
   4.853788793123566E-04  -8.767585921516854E-04  -3.565134847529999E-04
  -8.767585921516855E-04   3.797806257029667E-04  -8.767585921516806E-04
  -3.565134847529996E-04  -8.767585921516788E-04   4.853788793123582E-04
      </IFC>
    </s_s1_m1_m2_m3.1.2.4.2.2>
    <s_s1_m1_m2_m3.1.2.1.3.2>
      <IFC>
   7.255340031788633E-04  -8.494255506852340E-04   8.494255506852409E-04
  -8.494255506852357E-04   7.255340031788659E-04   8.494255506852370E-04
   8.494255506852379E-04   8.494255506852392E-04   7.255340031788651E-04
      </IFC>
    </s_s1_m1_m2_m3.1.2.1.3.2>
    <s_s1_m1_m2_m3.1.2.2.3.2>
      <IFC>
   7.255340031788571E-04   8.494255506852349E-04   8.494255506852372E-04
   8.494255506852344E-04   7.255340031788549E-04  -8.494255506852298E-04
   8.494255506852360E-04  -8.494255506852313E-04   7.255340031788570E-04
      </IFC>
    </s_s1_m1_m2_m3.1.2.2.3.2>
    <s_s1_m1_m2_m3.1.2.3.3.2>
      <IFC>
   3.567031013005720E-04   1.772265613279903E-04  -1.453098128035494E-04
   1.772265613279892E-04   3.385018625114097E-04  -1.772265613279853E-04
  -1.453098128035542E-04  -1.772265613279840E-04   3.567031013005741E-04
      </IFC>
    </s_s1_m1_m2_m3.1.2.3.3.2>
    <s_s1_m1_m2_m3.1.2.4.3.2>
      <IFC>
   3.567031013005712E-04  -1.772265613279841E-04  -1.453098128035549E-04
  -1.772265613279858E-04   3.385018625114059E-04   1.772265613279856E-04
  -1.453098128035541E-04   1.772265613279868E-04   3.567031013005709E-04
      </IFC>
    </s_s1_m1_m2_m3.1.2.4.3.2>
    <s_s1_m1_m2_m3.1.2.1.4.2>
      <IFC>
  -4.870216683949655E-04   1.177690720465717E-03  -6.445264063880101E-04
   1.177690720465719E-03  -4.023796425073010E-03   1.177690720465721E-03
  -6.445264063880113E-04   1.177690720465723E-03  -4.870216683949579E-04
      </IFC>
    </s_s1_m1_m2_m3.1.2.1.4.2>
    <s_s1_m1_m2_m3.1.2.2.4.2>
      <IFC>
   3.385018625114020E-04   1.772265613279771E-04   1.772265613279722E-04
   1.772265613279755E-04   3.567031013005662E-04   1.453098128035492E-04
   1.772265613279706E-04   1.453098128035485E-04   3.567031013005675E-04
      </IFC>
    </s_s1_m1_m2_m3.1.2.2.4.2>
    <s_s1_m1_m2_m3.1.2.3.4.2>
      <IFC>
   6.371567834511233E-04  -2.041773192311471E-04   2.041773192311301E-04
  -2.041773192311466E-04   6.371567834511248E-04  -2.041773192311464E-04
   2.041773192311274E-04  -2.041773192311467E-04   6.371567834511314E-04
      </IFC>
    </s_s1_m1_m2_m3.1.2.3.4.2>
    <s_s1_m1_m2_m3.1.2.4.4.2>
      <IFC>
   3.567031013005630E-04   1.453098128035557E-04   1.772265613279707E-04
   1.453098128035561E-04   3.567031013005653E-04   1.772265613279767E-04
   1.772265613279691E-04   1.772265613279763E-04   3.385018625114049E-04
      </IFC>
    </s_s1_m1_m2_m3.1.2.4.4.2>
    <s_s1_m1_m2_m3.1.2.1.1.3>
      <IFC>
   1.870730363497802E-05   1.974951642236267E-05   3.627645821839241E-04
   1.974951642235920E-05   1.870730363497802E-05   3.627645821839276E-04
   3.627645821839207E-04   3.627645821839311E-04  -5.593567558623280E-05
      </IFC>
    </s_s1_m1_m2_m3.1.2.1.1.3>
    <s_s1_m1_m2_m3.1.2.2.1.3>
      <IFC>
   3.567031013005594E-04  -1.772265613279718E-04   1.453098128035545E-04
  -1.772265613279722E-04   3.385018625113982E-04  -1.772265613279715E-04
   1.453098128035552E-04  -1.772265613279699E-04   3.567031013005577E-04
      </IFC>
    </s_s1_m1_m2_m3.1.2.2.1.3>
    <s_s1_m1_m2_m3.1.2.3.1.3>
      <IFC>
  -5.593567558622543E-05   3.627645821839264E-04   3.627645821839284E-04
   3.627645821839267E-04   1.870730363497824E-05   1.974951642235551E-05
   3.627645821839276E-04   1.974951642235790E-05   1.870730363497542E-05
      </IFC>
    </s_s1_m1_m2_m3.1.2.3.1.3>
    <s_s1_m1_m2_m3.1.2.4.1.3>
      <IFC>
   3.405968067643637E-04  -1.636759659108884E-04   1.636759659108786E-04
  -1.636759659108895E-04   3.405968067643634E-04  -1.636759659108826E-04
   1.636759659108794E-04  -1.636759659108804E-04   3.405968067643585E-04
      </IFC>
    </s_s1_m1_m2_m3.1.2.4.1.3>
    <s_s1_m1_m2_m3.1.2.1.2.3>
      <IFC>
  -4.870216683949685E-04   6.445264063880130E-04   1.177690720465707E-03
   6.445264063880130E-04  -4.870216683949616E-04  -1.177690720465724E-03
   1.177690720465710E-03  -1.177690720465720E-03  -4.023796425073008E-03
      </IFC>
    </s_s1_m1_m2_m3.1.2.1.2.3>
    <s_s1_m1_m2_m3.1.2.2.2.3>
      <IFC>
  -4.023796425073016E-03  -1.177690720465721E-03   1.177690720465707E-03
  -1.177690720465720E-03  -4.870216683949698E-04   6.445264063880077E-04
   1.177690720465707E-03   6.445264063880110E-04  -4.870216683949694E-04
      </IFC>
    </s_s1_m1_m2_m3.1.2.2.2.3>
    <s_s1_m1_m2_m3.1.2.3.2.3>
      <IFC>
  -5.593567558624354E-05  -3.627645821839213E-04  -3.627645821839268E-04
  -3.627645821839216E-04   1.870730363496675E-05   1.974951642236928E-05
  -3.627645821839271E-04   1.974951642237058E-05   1.870730363496493E-05
      </IFC>
    </s_s1_m1_m2_m3.1.2.3.2.3>
    <s_s1_m1_m2_m3.1.2.4.2.3>
      <IFC>
   1.870730363495721E-05   1.974951642237308E-05  -3.627645821839345E-04
   1.974951642237308E-05   1.870730363495721E-05  -3.627645821839241E-04
  -3.627645821839276E-04  -3.627645821839137E-04  -5.593567558625362E-05
      </IFC>
    </s_s1_m1_m2_m3.1.2.4.2.3>
    <s_s1_m1_m2_m3.1.2.1.3.3>
      <IFC>
  -4.870216683949789E-04  -1.177690720465718E-03  -6.445264063880077E-04
  -1.177690720465717E-03  -4.023796425073023E-03  -1.177690720465709E-03
  -6.445264063880112E-04  -1.177690720465707E-03  -4.870216683949824E-04
      </IFC>
    </s_s1_m1_m2_m3.1.2.1.3.3>
    <s_s1_m1_m2_m3.1.2.2.3.3>
      <IFC>
   3.567031013005707E-04  -1.453098128035539E-04   1.772265613279889E-04
  -1.453098128035539E-04   3.567031013005718E-04  -1.772265613279866E-04
   1.772265613279887E-04  -1.772265613279847E-04   3.385018625114053E-04
      </IFC>
    </s_s1_m1_m2_m3.1.2.2.3.3>
    <s_s1_m1_m2_m3.1.2.3.3.3>
      <IFC>
   6.371567834511373E-04   2.041773192311345E-04   2.041773192311443E-04
   2.041773192311348E-04   6.371567834511349E-04   2.041773192311364E-04
   2.041773192311427E-04   2.041773192311385E-04   6.371567834511306E-04
      </IFC>
    </s_s1_m1_m2_m3.1.2.3.3.3>
    <s_s1_m1_m2_m3.1.2.4.3.3>
      <IFC>
   3.385018625114060E-04  -1.772265613279854E-04   1.772265613279796E-04
  -1.772265613279860E-04   3.567031013005673E-04  -1.453098128035579E-04
   1.772265613279796E-04  -1.453098128035557E-04   3.567031013005653E-04
      </IFC>
    </s_s1_m1_m2_m3.1.2.4.3.3>
    <s_s1_m1_m2_m3.1.2.1.4.3>
      <IFC>
   1.870730363496805E-05  -3.627645821839147E-04  -1.974951642236852E-05
  -3.627645821839168E-04  -5.593567558623042E-05   3.627645821839268E-04
  -1.974951642236798E-05   3.627645821839276E-04   1.870730363497257E-05
      </IFC>
    </s_s1_m1_m2_m3.1.2.1.4.3>
    <s_s1_m1_m2_m3.1.2.2.4.3>
      <IFC>
   6.371567834511233E-04   2.041773192311374E-04  -2.041773192311431E-04
   2.041773192311385E-04   6.371567834511289E-04  -2.041773192311374E-04
  -2.041773192311448E-04  -2.041773192311372E-04   6.371567834511250E-04
      </IFC>
    </s_s1_m1_m2_m3.1.2.2.4.3>
    <s_s1_m1_m2_m3.1.2.3.4.3>
      <IFC>
   6.371567834511195E-04  -2.041773192311375E-04  -2.041773192311428E-04
  -2.041773192311409E-04   6.371567834511191E-04   2.041773192311399E-04
  -2.041773192311441E-04   2.041773192311410E-04   6.371567834511194E-04
      </IFC>
    </s_s1_m1_m2_m3.1.2.3.4.3>
    <s_s1_m1_m2_m3.1.2.4.4.3>
      <IFC>
   1.870730363497629E-05   3.627645821839311E-04  -1.974951642236180E-05
   3.627645821839302E-04  -5.593567558622586E-05  -3.627645821839241E-04
  -1.974951642236527E-05  -3.627645821839215E-04   1.870730363496935E-05
      </IFC>
    </s_s1_m1_m2_m3.1.2.4.4.3>
    <s_s1_m1_m2_m3.1.2.1.1.4>
      <IFC>
   4.853788793123554E-04  -8.767585921516962E-04   3.565134847530031E-04
  -8.767585921516936E-04   3.797806257029709E-04   8.767585921517019E-04
   3.565134847529992E-04   8.767585921517040E-04   4.853788793123589E-04
      </IFC>
    </s_s1_m1_m2_m3.1.2.1.1.4>
    <s_s1_m1_m2_m3.1.2.2.1.4>
      <IFC>
   4.853788793123599E-04   8.767585921517004E-04   3.565134847529998E-04
   8.767585921516993E-04   3.797806257029688E-04  -8.767585921516990E-04
   3.565134847530001E-04  -8.767585921516998E-04   4.853788793123618E-04
      </IFC>
    </s_s1_m1_m2_m3.1.2.2.1.4>
    <s_s1_m1_m2_m3.1.2.3.1.4>
      <IFC>
   3.405968067643674E-04   1.636759659108717E-04  -1.636759659108880E-04
   1.636759659108694E-04   3.405968067643635E-04  -1.636759659108867E-04
  -1.636759659108928E-04  -1.636759659108858E-04   3.405968067643679E-04
      </IFC>
    </s_s1_m1_m2_m3.1.2.3.1.4>
    <s_s1_m1_m2_m3.1.2.4.1.4>
      <IFC>
   3.405968067643647E-04  -1.636759659108896E-04  -1.636759659108882E-04
  -1.636759659108905E-04   3.405968067643604E-04   1.636759659108743E-04
  -1.636759659108890E-04   1.636759659108749E-04   3.405968067643632E-04
      </IFC>
    </s_s1_m1_m2_m3.1.2.4.1.4>
    <s_s1_m1_m2_m3.1.2.1.2.4>
      <IFC>
  -7.109230137579478E-02   4.648977156803537E-02  -4.648977156803538E-02
   4.648977156803537E-02  -7.109230137579478E-02   4.648977156803537E-02
  -4.648977156803538E-02   4.648977156803537E-02  -7.109230137579478E-02
      </IFC>
    </s_s1_m1_m2_m3.1.2.1.2.4>
    <s_s1_m1_m2_m3.1.2.2.2.4>
      <IFC>
   4.853788793123542E-04  -3.565134847530020E-04  -8.767585921516870E-04
  -3.565134847530017E-04   4.853788793123535E-04  -8.767585921516774E-04
  -8.767585921516878E-04  -8.767585921516779E-04   3.797806257029691E-04
      </IFC>
    </s_s1_m1_m2_m3.1.2.2.2.4>
    <s_s1_m1_m2_m3.1.2.3.2.4>
      <IFC>
   1.870730363496328E-05  -3.627645821839249E-04   1.974951642237958E-05
  -3.627645821839236E-04  -5.593567558624739E-05  -3.627645821839160E-04
   1.974951642237709E-05  -3.627645821839151E-04   1.870730363496493E-05
      </IFC>
    </s_s1_m1_m2_m3.1.2.3.2.4>
    <s_s1_m1_m2_m3.1.2.4.2.4>
      <IFC>
   3.797806257029758E-04  -8.767585921516819E-04  -8.767585921516846E-04
  -8.767585921516818E-04   4.853788793123588E-04  -3.565134847530039E-04
  -8.767585921516849E-04  -3.565134847530023E-04   4.853788793123631E-04
      </IFC>
    </s_s1_m1_m2_m3.1.2.4.2.4>
    <s_s1_m1_m2_m3.1.2.1.3.4>
      <IFC>
   4.853788793123572E-04  -3.565134847530013E-04   8.767585921516841E-04
  -3.565134847530013E-04   4.853788793123580E-04   8.767585921516810E-04
   8.767585921516836E-04   8.767585921516823E-04   3.797806257029735E-04
      </IFC>
    </s_s1_m1_m2_m3.1.2.1.3.4>
    <s_s1_m1_m2_m3.1.2.2.3.4>
      <IFC>
   3.567031013005736E-04  -1.453098128035500E-04  -1.772265613279914E-04
  -1.453098128035503E-04   3.567031013005737E-04   1.772265613279838E-04
  -1.772265613279930E-04   1.772265613279835E-04   3.385018625114089E-04
      </IFC>
    </s_s1_m1_m2_m3.1.2.2.3.4>
    <s_s1_m1_m2_m3.1.2.3.3.4>
      <IFC>
   3.385018625114084E-04   1.772265613279804E-04  -1.772265613279923E-04
   1.772265613279806E-04   3.567031013005681E-04  -1.453098128035546E-04
  -1.772265613279944E-04  -1.453098128035542E-04   3.567031013005681E-04
      </IFC>
    </s_s1_m1_m2_m3.1.2.3.3.4>
    <s_s1_m1_m2_m3.1.2.4.3.4>
      <IFC>
   3.797806257029754E-04   8.767585921516855E-04   8.767585921516897E-04
   8.767585921516862E-04   4.853788793123611E-04  -3.565134847529950E-04
   8.767585921516909E-04  -3.565134847529958E-04   4.853788793123632E-04
      </IFC>
    </s_s1_m1_m2_m3.1.2.4.3.4>
    <s_s1_m1_m2_m3.1.2.1.4.4>
      <IFC>
  -5.593567558624018E-05  -3.627645821839171E-04   3.627645821839269E-04
  -3.627645821839167E-04   1.870730363497542E-05  -1.974951642236690E-05
   3.627645821839275E-04  -1.974951642236874E-05   1.870730363497480E-05
      </IFC>
    </s_s1_m1_m2_m3.1.2.1.4.4>
    <s_s1_m1_m2_m3.1.2.2.4.4>
      <IFC>
   3.567031013005619E-04   1.772265613279680E-04   1.453098128035608E-04
   1.772265613279662E-04   3.385018625114002E-04   1.772265613279717E-04
   1.453098128035594E-04   1.772265613279716E-04   3.567031013005652E-04
      </IFC>
    </s_s1_m1_m2_m3.1.2.2.4.4>
    <s_s1_m1_m2_m3.1.2.3.4.4>
      <IFC>
   1.870730363497108E-05  -1.974951642236101E-05   3.627645821839337E-04
  -1.974951642236183E-05   1.870730363497098E-05  -3.627645821839262E-04
   3.627645821839310E-04  -3.627645821839266E-04  -5.593567558623009E-05
      </IFC>
    </s_s1_m1_m2_m3.1.2.3.4.4>
    <s_s1_m1_m2_m3.1.2.4.4.4>
      <IFC>
   3.405968067643469E-04   1.636759659108891E-04   1.636759659108797E-04
   1.636759659108888E-04   3.405968067643481E-04   1.636759659108963E-04
   1.636759659108796E-04   1.636759659108966E-04   3.405968067643510E-04
      </IFC>
    </s_s1_m1_m2_m3.1.2.4.4.4>
    <s_s1_m1_m2_m3.2.1.1.1.1>
      <IFC>
  -7.109230137579478E-02  -4.648977156803538E-02  -4.648977156803537E-02
  -4.648977156803537E-02  -7.109230137579478E-02  -4.648977156803538E-02
  -4.648977156803537E-02  -4.648977156803538E-02  -7.109230137579478E-02
      </IFC>
    </s_s1_m1_m2_m3.2.1.1.1.1>
    <s_s1_m1_m2_m3.2.1.2.1.1>
      <IFC>
   4.853788793123602E-04   3.565134847530005E-04  -8.767585921516972E-04
   3.565134847530004E-04   4.853788793123565E-04   8.767585921517012E-04
  -8.767585921516952E-04   8.767585921516995E-04   3.797806257029770E-04
      </IFC>
    </s_s1_m1_m2_m3.2.1.2.1.1>
    <s_s1_m1_m2_m3.2.1.3.1.1>
      <IFC>
   1.870730363497499E-05   3.627645821839285E-04   1.974951642235313E-05
   3.627645821839279E-04  -5.593567558623649E-05   3.627645821839324E-04
   1.974951642235757E-05   3.627645821839322E-04   1.870730363497542E-05
      </IFC>
    </s_s1_m1_m2_m3.2.1.3.1.1>
    <s_s1_m1_m2_m3.2.1.4.1.1>
      <IFC>
   3.797806257029694E-04   8.767585921516958E-04  -8.767585921517033E-04
   8.767585921516952E-04   4.853788793123512E-04   3.565134847530016E-04
  -8.767585921517011E-04   3.565134847530022E-04   4.853788793123561E-04
      </IFC>
    </s_s1_m1_m2_m3.2.1.4.1.1>
    <s_s1_m1_m2_m3.2.1.1.2.1>
      <IFC>
  -4.023796425073008E-03   1.177690720465721E-03   1.177690720465710E-03
   1.177690720465721E-03  -4.870216683949523E-04  -6.445264063880199E-04
   1.177690720465711E-03  -6.445264063880189E-04  -4.870216683949566E-04
      </IFC>
    </s_s1_m1_m2_m3.2.1.1.2.1>
    <s_s1_m1_m2_m3.2.1.2.2.1>
      <IFC>
  -5.593567558624148E-05   3.627645821839319E-04  -3.627645821839198E-04
   3.627645821839345E-04   1.870730363496415E-05  -1.974951642237047E-05
  -3.627645821839181E-04  -1.974951642237134E-05   1.870730363497282E-05
      </IFC>
    </s_s1_m1_m2_m3.2.1.2.2.1>
    <s_s1_m1_m2_m3.2.1.3.2.1>
      <IFC>
   1.870730363497314E-05  -1.974951642237175E-05  -3.627645821839156E-04
  -1.974951642237115E-05   1.870730363496854E-05   3.627645821839340E-04
  -3.627645821839132E-04   3.627645821839314E-04  -5.593567558623275E-05
      </IFC>
    </s_s1_m1_m2_m3.2.1.3.2.1>
    <s_s1_m1_m2_m3.2.1.4.2.1>
      <IFC>
  -4.870216683949616E-04  -6.445264063880140E-04   1.177690720465707E-03
  -6.445264063880130E-04  -4.870216683949629E-04   1.177690720465725E-03
   1.177690720465710E-03   1.177690720465726E-03  -4.023796425073010E-03
      </IFC>
    </s_s1_m1_m2_m3.2.1.4.2.1>
    <s_s1_m1_m2_m3.2.1.1.3.1>
      <IFC>
  -4.023796425073025E-03  -1.177690720465722E-03  -1.177690720465722E-03
  -1.177690720465720E-03  -4.870216683949772E-04  -6.445264063880017E-04
  -1.177690720465722E-03  -6.445264063880034E-04  -4.870216683949755E-04
      </IFC>
    </s_s1_m1_m2_m3.2.1.1.3.1>
    <s_s1_m1_m2_m3.2.1.2.3.1>
      <IFC>
   4.853788793123576E-04   8.767585921516780E-04  -3.565134847530099E-04
   8.767585921516781E-04   3.797806257029655E-04   8.767585921516800E-04
  -3.565134847530093E-04   8.767585921516791E-04   4.853788793123589E-04
      </IFC>
    </s_s1_m1_m2_m3.2.1.2.3.1>
    <s_s1_m1_m2_m3.2.1.3.3.1>
      <IFC>
  -4.870216683949748E-04  -6.445264063879995E-04  -1.177690720465721E-03
  -6.445264063879992E-04  -4.870216683949801E-04  -1.177690720465714E-03
  -1.177690720465717E-03  -1.177690720465717E-03  -4.023796425073025E-03
      </IFC>
    </s_s1_m1_m2_m3.2.1.3.3.1>
    <s_s1_m1_m2_m3.2.1.4.3.1>
      <IFC>
   7.255340031788692E-04   8.494255506852405E-04  -8.494255506852291E-04
   8.494255506852406E-04   7.255340031788633E-04   8.494255506852429E-04
  -8.494255506852274E-04   8.494255506852431E-04   7.255340031788705E-04
      </IFC>
    </s_s1_m1_m2_m3.2.1.4.3.1>
    <s_s1_m1_m2_m3.2.1.1.4.1>
      <IFC>
  -7.109230137579479E-02   4.648977156803537E-02   4.648977156803537E-02
   4.648977156803537E-02  -7.109230137579478E-02  -4.648977156803537E-02
   4.648977156803537E-02  -4.648977156803537E-02  -7.109230137579478E-02
      </IFC>
    </s_s1_m1_m2_m3.2.1.1.4.1>
    <s_s1_m1_m2_m3.2.1.2.4.1>
      <IFC>
  -7.109230137579478E-02  -4.648977156803537E-02   4.648977156803537E-02
  -4.648977156803537E-02  -7.109230137579478E-02   4.648977156803538E-02
   4.648977156803537E-02   4.648977156803538E-02  -7.109230137579478E-02
      </IFC>
    </s_s1_m1_m2_m3.2.1.2.4.1>
    <s_s1_m1_m2_m3.2.1.3.4.1>
      <IFC>
  -4.870216683949613E-04   1.177690720465706E-03   6.445264063880118E-04
   1.177690720465706E-03  -4.023796425073014E-03  -1.177690720465720E-03
   6.445264063880131E-04  -1.177690720465725E-03  -4.870216683949603E-04
      </IFC>
    </s_s1_m1_m2_m3.2.1.3.4.1>
    <s_s1_m1_m2_m3.2.1.4.4.1>
      <IFC>
  -4.870216683949668E-04  -1.177690720465725E-03   6.445264063880121E-04
  -1.177690720465725E-03  -4.023796425073020E-03   1.177690720465707E-03
   6.445264063880138E-04   1.177690720465708E-03  -4.870216683949668E-04
      </IFC>
    </s_s1_m1_m2_m3.2.1.4.4.1>
    <s_s1_m1_m2_m3.2.1.1.1.2>
      <IFC>
   4.853788793123554E-04  -8.767585921516936E-04   3.565134847529992E-04
  -8.767585921516962E-04   3.797806257029709E-04   8.767585921517040E-04
   3.565134847530031E-04   8.767585921517019E-04   4.853788793123589E-04
      </IFC>
    </s_s1_m1_m2_m3.2.1.1.1.2>
    <s_s1_m1_m2_m3.2.1.2.1.2>
      <IFC>
   3.405968067643647E-04  -1.636759659108905E-04  -1.636759659108890E-04
  -1.636759659108896E-04   3.405968067643604E-04   1.636759659108749E-04
  -1.636759659108882E-04   1.636759659108743E-04   3.405968067643632E-04
      </IFC>
    </s_s1_m1_m2_m3.2.1.2.1.2>
    <s_s1_m1_m2_m3.2.1.3.1.2>
      <IFC>
   3.405968067643674E-04   1.636759659108694E-04  -1.636759659108928E-04
   1.636759659108717E-04   3.405968067643635E-04  -1.636759659108858E-04
  -1.636759659108880E-04  -1.636759659108867E-04   3.405968067643679E-04
      </IFC>
    </s_s1_m1_m2_m3.2.1.3.1.2>
    <s_s1_m1_m2_m3.2.1.4.1.2>
      <IFC>
   4.853788793123599E-04   8.767585921516993E-04   3.565134847530001E-04
   8.767585921517004E-04   3.797806257029688E-04  -8.767585921516998E-04
   3.565134847529998E-04  -8.767585921516990E-04   4.853788793123618E-04
      </IFC>
    </s_s1_m1_m2_m3.2.1.4.1.2>
    <s_s1_m1_m2_m3.2.1.1.2.2>
      <IFC>
  -5.593567558624018E-05  -3.627645821839167E-04   3.627645821839275E-04
  -3.627645821839171E-04   1.870730363497542E-05  -1.974951642236874E-05
   3.627645821839269E-04  -1.974951642236690E-05   1.870730363497480E-05
      </IFC>
    </s_s1_m1_m2_m3.2.1.1.2.2>
    <s_s1_m1_m2_m3.2.1.2.2.2>
      <IFC>
   3.405968067643469E-04   1.636759659108888E-04   1.636759659108796E-04
   1.636759659108891E-04   3.405968067643481E-04   1.636759659108966E-04
   1.636759659108797E-04   1.636759659108963E-04   3.405968067643510E-04
      </IFC>
    </s_s1_m1_m2_m3.2.1.2.2.2>
    <s_s1_m1_m2_m3.2.1.3.2.2>
      <IFC>
   1.870730363497108E-05  -1.974951642236183E-05   3.627645821839310E-04
  -1.974951642236101E-05   1.870730363497098E-05  -3.627645821839266E-04
   3.627645821839337E-04  -3.627645821839262E-04  -5.593567558623009E-05
      </IFC>
    </s_s1_m1_m2_m3.2.1.3.2.2>
    <s_s1_m1_m2_m3.2.1.4.2.2>
      <IFC>
   3.567031013005619E-04   1.772265613279662E-04   1.453098128035594E-04
   1.772265613279680E-04   3.385018625114002E-04   1.772265613279716E-04
   1.453098128035608E-04   1.772265613279717E-04   3.567031013005652E-04
      </IFC>
    </s_s1_m1_m2_m3.2.1.4.2.2>
    <s_s1_m1_m2_m3.2.1.1.3.2>
      <IFC>
   4.853788793123572E-04  -3.565134847530013E-04   8.767585921516836E-04
  -3.565134847530013E-04   4.853788793123580E-04   8.767585921516823E-04
   8.767585921516841E-04   8.767585921516810E-04   3.797806257029735E-04
      </IFC>
    </s_s1_m1_m2_m3.2.1.1.3.2>
    <s_s1_m1_m2_m3.2.1.2.3.2>
      <IFC>
   3.797806257029754E-04   8.767585921516862E-04   8.767585921516909E-04
   8.767585921516855E-04   4.853788793123611E-04  -3.565134847529958E-04
   8.767585921516897E-04  -3.565134847529950E-04   4.853788793123632E-04
      </IFC>
    </s_s1_m1_m2_m3.2.1.2.3.2>
    <s_s1_m1_m2_m3.2.1.3.3.2>
      <IFC>
   3.385018625114084E-04   1.772265613279806E-04  -1.772265613279944E-04
   1.772265613279804E-04   3.567031013005681E-04  -1.453098128035542E-04
  -1.772265613279923E-04  -1.453098128035546E-04   3.567031013005681E-04
      </IFC>
    </s_s1_m1_m2_m3.2.1.3.3.2>
    <s_s1_m1_m2_m3.2.1.4.3.2>
      <IFC>
   3.567031013005736E-04  -1.453098128035503E-04  -1.772265613279930E-04
  -1.453098128035500E-04   3.567031013005737E-04   1.772265613279835E-04
  -1.772265613279914E-04   1.772265613279838E-04   3.385018625114089E-04
      </IFC>
    </s_s1_m1_m2_m3.2.1.4.3.2>
    <s_s1_m1_m2_m3.2.1.1.4.2>
      <IFC>
  -7.109230137579478E-02   4.648977156803537E-02  -4.648977156803538E-02
   4.648977156803537E-02  -7.109230137579478E-02   4.648977156803537E-02
  -4.648977156803538E-02   4.648977156803537E-02  -7.109230137579478E-02
      </IFC>
    </s_s1_m1_m2_m3.2.1.1.4.2>
    <s_s1_m1_m2_m3.2.1.2.4.2>
      <IFC>
   3.797806257029758E-04  -8.767585921516818E-04  -8.767585921516849E-04
  -8.767585921516819E-04   4.853788793123588E-04  -3.565134847530023E-04
  -8.767585921516846E-04  -3.565134847530039E-04   4.853788793123631E-04
      </IFC>
    </s_s1_m1_m2_m3.2.1.2.4.2>
    <s_s1_m1_m2_m3.2.1.3.4.2>
      <IFC>
   1.870730363496328E-05  -3.627645821839236E-04   1.974951642237709E-05
  -3.627645821839249E-04  -5.593567558624739E-05  -3.627645821839151E-04
   1.974951642237958E-05  -3.627645821839160E-04   1.870730363496493E-05
      </IFC>
    </s_s1_m1_m2_m3.2.1.3.4.2>
    <s_s1_m1_m2_m3.2.1.4.4.2>
      <IFC>
   4.853788793123542E-04  -3.565134847530017E-04  -8.767585921516878E-04
  -3.565134847530020E-04   4.853788793123535E-04  -8.767585921516779E-04
  -8.767585921516870E-04  -8.767585921516774E-04   3.797806257029691E-04
      </IFC>
    </s_s1_m1_m2_m3.2.1.4.4.2>
    <s_s1_m1_m2_m3.2.1.1.1.3>
      <IFC>
   1.870730363497802E-05   1.974951642235920E-05   3.627645821839207E-04
   1.974951642236267E-05   1.870730363497802E-05   3.627645821839311E-04
   3.627645821839241E-04   3.627645821839276E-04  -5.593567558623280E-05
      </IFC>
    </s_s1_m1_m2_m3.2.1.1.1.3>
    <s_s1_m1_m2_m3.2.1.2.1.3>
      <IFC>
   3.405968067643637E-04  -1.636759659108895E-04   1.636759659108794E-04
  -1.636759659108884E-04   3.405968067643634E-04  -1.636759659108804E-04
   1.636759659108786E-04  -1.636759659108826E-04   3.405968067643585E-04
      </IFC>
    </s_s1_m1_m2_m3.2.1.2.1.3>
    <s_s1_m1_m2_m3.2.1.3.1.3>
      <IFC>
  -5.593567558622543E-05   3.627645821839267E-04   3.627645821839276E-04
   3.627645821839264E-04   1.870730363497824E-05   1.974951642235790E-05
   3.627645821839284E-04   1.974951642235551E-05   1.870730363497542E-05
      </IFC>
    </s_s1_m1_m2_m3.2.1.3.1.3>
    <s_s1_m1_m2_m3.2.1.4.1.3>
      <IFC>
   3.567031013005594E-04  -1.772265613279722E-04   1.453098128035552E-04
  -1.772265613279718E-04   3.385018625113982E-04  -1.772265613279699E-04
   1.453098128035545E-04  -1.772265613279715E-04   3.567031013005577E-04
      </IFC>
    </s_s1_m1_m2_m3.2.1.4.1.3>
    <s_s1_m1_m2_m3.2.1.1.2.3>
      <IFC>
   1.870730363496805E-05  -3.627645821839168E-04  -1.974951642236798E-05
  -3.627645821839147E-04  -5.593567558623042E-05   3.627645821839276E-04
  -1.974951642236852E-05   3.627645821839268E-04   1.870730363497257E-05
      </IFC>
    </s_s1_m1_m2_m3.2.1.1.2.3>
    <s_s1_m1_m2_m3.2.1.2.2.3>
      <IFC>
   1.870730363497629E-05   3.627645821839302E-04  -1.974951642236527E-05
   3.627645821839311E-04  -5.593567558622586E-05  -3.627645821839215E-04
  -1.974951642236180E-05  -3.627645821839241E-04   1.870730363496935E-05
      </IFC>
    </s_s1_m1_m2_m3.2.1.2.2.3>
    <s_s1_m1_m2_m3.2.1.3.2.3>
      <IFC>
   6.371567834511195E-04  -2.041773192311409E-04  -2.041773192311441E-04
  -2.041773192311375E-04   6.371567834511191E-04   2.041773192311410E-04
  -2.041773192311428E-04   2.041773192311399E-04   6.371567834511194E-04
      </IFC>
    </s_s1_m1_m2_m3.2.1.3.2.3>
    <s_s1_m1_m2_m3.2.1.4.2.3>
      <IFC>
   6.371567834511233E-04   2.041773192311385E-04  -2.041773192311448E-04
   2.041773192311374E-04   6.371567834511289E-04  -2.041773192311372E-04
  -2.041773192311431E-04  -2.041773192311374E-04   6.371567834511250E-04
      </IFC>
    </s_s1_m1_m2_m3.2.1.4.2.3>
    <s_s1_m1_m2_m3.2.1.1.3.3>
      <IFC>
  -4.870216683949789E-04  -1.177690720465717E-03  -6.445264063880112E-04
  -1.177690720465718E-03  -4.023796425073023E-03  -1.177690720465707E-03
  -6.445264063880077E-04  -1.177690720465709E-03  -4.870216683949824E-04
      </IFC>
    </s_s1_m1_m2_m3.2.1.1.3.3>
    <s_s1_m1_m2_m3.2.1.2.3.3>
      <IFC>
   3.385018625114060E-04  -1.772265613279860E-04   1.772265613279796E-04
  -1.772265613279854E-04   3.567031013005673E-04  -1.453098128035557E-04
   1.772265613279796E-04  -1.453098128035579E-04   3.567031013005653E-04
      </IFC>
    </s_s1_m1_m2_m3.2.1.2.3.3>
    <s_s1_m1_m2_m3.2.1.3.3.3>
      <IFC>
   6.371567834511373E-04   2.041773192311348E-04   2.041773192311427E-04
   2.041773192311345E-04   6.371567834511349E-04   2.041773192311385E-04
   2.041773192311443E-04   2.041773192311364E-04   6.371567834511306E-04
      </IFC>
    </s_s1_m1_m2_m3.2.1.3.3.3>
    <s_s1_m1_m2_m3.2.1.4.3.3>
      <IFC>
   3.567031013005707E-04  -1.453098128035539E-04   1.772265613279887E-04
  -1.453098128035539E-04   3.567031013005718E-04  -1.772265613279847E-04
   1.772265613279889E-04  -1.772265613279866E-04   3.385018625114053E-04
      </IFC>
    </s_s1_m1_m2_m3.2.1.4.3.3>
    <s_s1_m1_m2_m3.2.1.1.4.3>
      <IFC>
  -4.870216683949685E-04   6.445264063880130E-04   1.177690720465710E-03
   6.445264063880130E-04  -4.870216683949616E-04  -1.177690720465720E-03
   1.177690720465707E-03  -1.177690720465724E-03  -4.023796425073008E-03
      </IFC>
    </s_s1_m1_m2_m3.2.1.1.4.3>
    <s_s1_m1_m2_m3.2.1.2.4.3>
      <IFC>
   1.870730363495721E-05   1.974951642237308E-05  -3.627645821839276E-04
   1.974951642237308E-05   1.870730363495721E-05  -3.627645821839137E-04
  -3.627645821839345E-04  -3.627645821839241E-04  -5.593567558625362E-05
      </IFC>
    </s_s1_m1_m2_m3.2.1.2.4.3>
    <s_s1_m1_m2_m3.2.1.3.4.3>
      <IFC>
  -5.593567558624354E-05  -3.627645821839216E-04  -3.627645821839271E-04
  -3.627645821839213E-04   1.870730363496675E-05   1.974951642237058E-05
  -3.627645821839268E-04   1.974951642236928E-05   1.870730363496493E-05
      </IFC>
    </s_s1_m1_m2_m3.2.1.3.4.3>
    <s_s1_m1_m2_m3.2.1.4.4.3>
      <IFC>
  -4.023796425073016E-03  -1.177690720465720E-03   1.177690720465707E-03
  -1.177690720465721E-03  -4.870216683949698E-04   6.445264063880110E-04
   1.177690720465707E-03   6.445264063880077E-04  -4.870216683949694E-04
      </IFC>
    </s_s1_m1_m2_m3.2.1.4.4.3>
    <s_s1_m1_m2_m3.2.1.1.1.4>
      <IFC>
   3.797806257029631E-04  -8.767585921516980E-04   8.767585921516854E-04
  -8.767585921516988E-04   4.853788793123476E-04   3.565134847530083E-04
   8.767585921516884E-04   3.565134847530070E-04   4.853788793123554E-04
      </IFC>
    </s_s1_m1_m2_m3.2.1.1.1.4>
    <s_s1_m1_m2_m3.2.1.2.1.4>
      <IFC>
   4.853788793123657E-04   3.565134847530071E-04   8.767585921516920E-04
   3.565134847530069E-04   4.853788793123637E-04  -8.767585921517017E-04
   8.767585921516914E-04  -8.767585921517008E-04   3.797806257029762E-04
      </IFC>
    </s_s1_m1_m2_m3.2.1.2.1.4>
    <s_s1_m1_m2_m3.2.1.3.1.4>
      <IFC>
   3.567031013005572E-04   1.453098128035633E-04  -1.772265613279663E-04
   1.453098128035627E-04   3.567031013005585E-04  -1.772265613279732E-04
  -1.772265613279641E-04  -1.772265613279732E-04   3.385018625113984E-04
      </IFC>
    </s_s1_m1_m2_m3.2.1.3.1.4>
    <s_s1_m1_m2_m3.2.1.4.1.4>
      <IFC>
   3.385018625113989E-04  -1.772265613279715E-04  -1.772265613279672E-04
  -1.772265613279718E-04   3.567031013005624E-04   1.453098128035643E-04
  -1.772265613279663E-04   1.453098128035644E-04   3.567031013005619E-04
      </IFC>
    </s_s1_m1_m2_m3.2.1.4.1.4>
    <s_s1_m1_m2_m3.2.1.1.2.4>
      <IFC>
  -4.870216683949655E-04   1.177690720465719E-03  -6.445264063880113E-04
   1.177690720465717E-03  -4.023796425073010E-03   1.177690720465723E-03
  -6.445264063880101E-04   1.177690720465721E-03  -4.870216683949579E-04
      </IFC>
    </s_s1_m1_m2_m3.2.1.1.2.4>
    <s_s1_m1_m2_m3.2.1.2.2.4>
      <IFC>
   3.567031013005630E-04   1.453098128035561E-04   1.772265613279691E-04
   1.453098128035557E-04   3.567031013005653E-04   1.772265613279763E-04
   1.772265613279707E-04   1.772265613279767E-04   3.385018625114049E-04
      </IFC>
    </s_s1_m1_m2_m3.2.1.2.2.4>
    <s_s1_m1_m2_m3.2.1.3.2.4>
      <IFC>
   6.371567834511233E-04  -2.041773192311466E-04   2.041773192311274E-04
  -2.041773192311471E-04   6.371567834511248E-04  -2.041773192311467E-04
   2.041773192311301E-04  -2.041773192311464E-04   6.371567834511314E-04
      </IFC>
    </s_s1_m1_m2_m3.2.1.3.2.4>
    <s_s1_m1_m2_m3.2.1.4.2.4>
      <IFC>
   3.385018625114020E-04   1.772265613279755E-04   1.772265613279706E-04
   1.772265613279771E-04   3.567031013005662E-04   1.453098128035485E-04
   1.772265613279722E-04   1.453098128035492E-04   3.567031013005675E-04
      </IFC>
    </s_s1_m1_m2_m3.2.1.4.2.4>
    <s_s1_m1_m2_m3.2.1.1.3.4>
      <IFC>
   7.255340031788633E-04  -8.494255506852357E-04   8.494255506852379E-04
  -8.494255506852340E-04   7.255340031788659E-04   8.494255506852392E-04
   8.494255506852409E-04   8.494255506852370E-04   7.255340031788651E-04
      </IFC>
    </s_s1_m1_m2_m3.2.1.1.3.4>
    <s_s1_m1_m2_m3.2.1.2.3.4>
      <IFC>
   3.567031013005712E-04  -1.772265613279858E-04  -1.453098128035541E-04
  -1.772265613279841E-04   3.385018625114059E-04   1.772265613279868E-04
  -1.453098128035549E-04   1.772265613279856E-04   3.567031013005709E-04
      </IFC>
    </s_s1_m1_m2_m3.2.1.2.3.4>
    <s_s1_m1_m2_m3.2.1.3.3.4>
      <IFC>
   3.567031013005720E-04   1.772265613279892E-04  -1.453098128035542E-04
   1.772265613279903E-04   3.385018625114097E-04  -1.772265613279840E-04
  -1.453098128035494E-04  -1.772265613279853E-04   3.567031013005741E-04
      </IFC>
    </s_s1_m1_m2_m3.2.1.3.3.4>
    <s_s1_m1_m2_m3.2.1.4.3.4>
      <IFC>
   7.255340031788571E-04   8.494255506852344E-04   8.494255506852360E-04
   8.494255506852349E-04   7.255340031788549E-04  -8.494255506852313E-04
   8.494255506852372E-04  -8.494255506852298E-04   7.255340031788570E-04
      </IFC>
    </s_s1_m1_m2_m3.2.1.4.3.4>
    <s_s1_m1_m2_m3.2.1.1.4.4>
      <IFC>
  -4.870216683949824E-04   6.445264063880164E-04  -1.177690720465724E-03
   6.445264063880164E-04  -4.870216683949616E-04   1.177690720465710E-03
  -1.177690720465724E-03   1.177690720465707E-03  -4.023796425073022E-03
      </IFC>
    </s_s1_m1_m2_m3.2.1.1.4.4>
    <s_s1_m1_m2_m3.2.1.2.4.4>
      <IFC>
   4.853788793123566E-04  -8.767585921516855E-04  -3.565134847529996E-04
  -8.767585921516854E-04   3.797806257029667E-04  -8.767585921516788E-04
  -3.565134847529999E-04  -8.767585921516806E-04   4.853788793123582E-04
      </IFC>
    </s_s1_m1_m2_m3.2.1.2.4.4>
    <s_s1_m1_m2_m3.2.1.3.4.4>
      <IFC>
  -4.023796425073019E-03   1.177690720465702E-03  -1.177690720465724E-03
   1.177690720465700E-03  -4.870216683949691E-04   6.445264063880152E-04
  -1.177690720465723E-03   6.445264063880146E-04  -4.870216683949645E-04
      </IFC>
    </s_s1_m1_m2_m3.2.1.3.4.4>
    <s_s1_m1_m2_m3.2.1.4.4.4>
      <IFC>
   7.255340031788853E-04  -8.494255506852393E-04  -8.494255506852481E-04
  -8.494255506852390E-04   7.255340031788852E-04  -8.494255506852358E-04
  -8.494255506852484E-04  -8.494255506852363E-04   7.255340031788876E-04
      </IFC>
    </s_s1_m1_m2_m3.2.1.4.4.4>
    <s_s1_m1_m2_m3.2.2.1.1.1>
      <IFC>
   2.848229995399654E-01  -7.589415207398531E-19  -6.505213034913027E-19
  -7.589415207398531E-19   2.848229995399654E-01  -2.331034670843835E-18
  -6.505213034913027E-19  -2.331034670843835E-18   2.848229995399654E-01
      </IFC>
    </s_s1_m1_m2_m3.2.2.1.1.1>
    <s_s1_m1_m2_m3.2.2.2.1.1>
      <IFC>
  -3.742641877241906E-03   1.862497946339836E-03   4.479053795943344E-03
  -1.862497946339841E-03   1.059986195261796E-02   1.862497946339837E-03
   4.479053795943344E-03  -1.862497946339839E-03  -3.742641877241905E-03
      </IFC>
    </s_s1_m1_m2_m3.2.2.2.1.1>
    <s_s1_m1_m2_m3.2.2.3.1.1>
      <IFC>
  -2.939277549420492E-05   4.607859233063394E-19   5.039471004495754E-04
   4.607859233063394E-19   4.088223787532453E-03  -5.963111948670274E-18
   5.039471004495754E-04  -5.963111948670274E-18  -2.939277549421707E-05
      </IFC>
    </s_s1_m1_m2_m3.2.2.3.1.1>
    <s_s1_m1_m2_m3.2.2.4.1.1>
      <IFC>
  -3.742641877241906E-03  -1.862497946339841E-03   4.479053795943344E-03
   1.862497946339836E-03   1.059986195261796E-02  -1.862497946339839E-03
   4.479053795943344E-03   1.862497946339837E-03  -3.742641877241905E-03
      </IFC>
    </s_s1_m1_m2_m3.2.2.4.1.1>
    <s_s1_m1_m2_m3.2.2.1.2.1>
      <IFC>
   1.059986195261797E-02  -1.862497946339840E-03  -1.862497946339838E-03
   1.862497946339837E-03  -3.742641877241912E-03  -4.479053795943343E-03
   1.862497946339839E-03  -4.479053795943343E-03  -3.742641877241906E-03
      </IFC>
    </s_s1_m1_m2_m3.2.2.1.2.1>
    <s_s1_m1_m2_m3.2.2.2.2.1>
      <IFC>
  -4.203739861953050E-04  -4.780808197830971E-04   4.856894729035851E-04
  -4.780808197830971E-04  -4.203739861953033E-04  -4.856894729035846E-04
   3.519910384011430E-04  -3.519910384011430E-04  -3.163771518603763E-04
      </IFC>
    </s_s1_m1_m2_m3.2.2.2.2.1>
    <s_s1_m1_m2_m3.2.2.3.2.1>
      <IFC>
  -3.163771518603625E-04  -3.519910384011424E-04   3.519910384011414E-04
  -4.856894729035844E-04  -4.203739861953059E-04  -4.780808197830946E-04
   4.856894729035834E-04  -4.780808197830946E-04  -4.203739861953042E-04
      </IFC>
    </s_s1_m1_m2_m3.2.2.3.2.1>
    <s_s1_m1_m2_m3.2.2.4.2.1>
      <IFC>
  -3.742641877241906E-03  -4.479053795943347E-03   1.862497946339838E-03
  -4.479053795943347E-03  -3.742641877241908E-03   1.862497946339843E-03
  -1.862497946339838E-03  -1.862497946339834E-03   1.059986195261796E-02
      </IFC>
    </s_s1_m1_m2_m3.2.2.4.2.1>
    <s_s1_m1_m2_m3.2.2.1.3.1>
      <IFC>
   4.088223787532451E-03   1.328147661294743E-18   1.192622389734055E-18
   1.328147661294743E-18  -2.939277549421360E-05  -5.039471004495801E-04
   1.192622389734055E-18  -5.039471004495801E-04  -2.939277549422747E-05
      </IFC>
    </s_s1_m1_m2_m3.2.2.1.3.1>
    <s_s1_m1_m2_m3.2.2.2.3.1>
      <IFC>
  -4.203739861953050E-04  -4.856894729035891E-04   4.780808197830969E-04
  -3.519910384011472E-04  -3.163771518603746E-04  -3.519910384011450E-04
   4.780808197830969E-04  -4.856894729035866E-04  -4.203739861952929E-04
      </IFC>
    </s_s1_m1_m2_m3.2.2.2.3.1>
    <s_s1_m1_m2_m3.2.2.3.3.1>
      <IFC>
  -2.939277549420492E-05  -5.039471004495829E-04   2.168404344971009E-19
  -5.039471004495829E-04  -2.939277549420492E-05  -1.734723475976807E-18
   2.168404344971009E-19  -1.734723475976807E-18   4.088223787532441E-03
      </IFC>
    </s_s1_m1_m2_m3.2.2.3.3.1>
    <s_s1_m1_m2_m3.2.2.4.3.1>
      <IFC>
  -4.203739861953050E-04  -3.519910384011472E-04   4.780808197830969E-04
  -4.856894729035891E-04  -3.163771518603746E-04  -4.856894729035866E-04
   4.780808197830969E-04  -3.519910384011450E-04  -4.203739861952929E-04
      </IFC>
    </s_s1_m1_m2_m3.2.2.4.3.1>
    <s_s1_m1_m2_m3.2.2.1.4.1>
      <IFC>
   1.059986195261797E-02   1.862497946339837E-03   1.862497946339839E-03
  -1.862497946339840E-03  -3.742641877241912E-03  -4.479053795943343E-03
  -1.862497946339838E-03  -4.479053795943343E-03  -3.742641877241906E-03
      </IFC>
    </s_s1_m1_m2_m3.2.2.1.4.1>
    <s_s1_m1_m2_m3.2.2.2.4.1>
      <IFC>
  -3.742641877241906E-03  -4.479053795943347E-03  -1.862497946339838E-03
  -4.479053795943347E-03  -3.742641877241908E-03  -1.862497946339834E-03
   1.862497946339838E-03   1.862497946339843E-03   1.059986195261796E-02
      </IFC>
    </s_s1_m1_m2_m3.2.2.2.4.1>
    <s_s1_m1_m2_m3.2.2.3.4.1>
      <IFC>
  -3.163771518603625E-04  -4.856894729035844E-04   4.856894729035834E-04
  -3.519910384011424E-04  -4.203739861953059E-04  -4.780808197830946E-04
   3.519910384011414E-04  -4.780808197830946E-04  -4.203739861953042E-04
      </IFC>
    </s_s1_m1_m2_m3.2.2.3.4.1>
    <s_s1_m1_m2_m3.2.2.4.4.1>
      <IFC>
  -4.203739861953050E-04  -4.780808197830971E-04   3.519910384011430E-04
  -4.780808197830971E-04  -4.203739861953033E-04  -3.519910384011430E-04
   4.856894729035851E-04  -4.856894729035846E-04  -3.163771518603763E-04
      </IFC>
    </s_s1_m1_m2_m3.2.2.4.4.1>
    <s_s1_m1_m2_m3.2.2.1.1.2>
      <IFC>
  -3.742641877241909E-03   4.479053795943343E-03   1.862497946339836E-03
   4.479053795943343E-03  -3.742641877241909E-03  -1.862497946339837E-03
  -1.862497946339841E-03   1.862497946339840E-03   1.059986195261794E-02
      </IFC>
    </s_s1_m1_m2_m3.2.2.1.1.2>
    <s_s1_m1_m2_m3.2.2.2.1.2>
      <IFC>
  -3.163771518603763E-04   3.519910384011417E-04   3.519910384011388E-04
   4.856894729035836E-04  -4.203739861953016E-04   4.780808197830952E-04
   4.856894729035807E-04   4.780808197830952E-04  -4.203739861953076E-04
      </IFC>
    </s_s1_m1_m2_m3.2.2.2.1.2>
    <s_s1_m1_m2_m3.2.2.3.1.2>
      <IFC>
  -4.203739861953076E-04   4.780808197831001E-04   4.856894729035807E-04
   4.780808197831001E-04  -4.203739861952990E-04   4.856894729035839E-04
   3.519910384011388E-04   3.519910384011421E-04  -3.163771518603694E-04
      </IFC>
    </s_s1_m1_m2_m3.2.2.3.1.2>
    <s_s1_m1_m2_m3.2.2.4.1.2>
      <IFC>
   1.059986195261796E-02   1.862497946339839E-03  -1.862497946339840E-03
  -1.862497946339838E-03  -3.742641877241906E-03   4.479053795943346E-03
   1.862497946339837E-03   4.479053795943346E-03  -3.742641877241907E-03
      </IFC>
    </s_s1_m1_m2_m3.2.2.4.1.2>
    <s_s1_m1_m2_m3.2.2.1.2.2>
      <IFC>
  -4.203739861953042E-04   4.856894729035866E-04  -4.780808197831013E-04
   3.519910384011446E-04  -3.163771518603677E-04  -3.519910384011421E-04
  -4.780808197831013E-04  -4.856894729035841E-04  -4.203739861953042E-04
      </IFC>
    </s_s1_m1_m2_m3.2.2.1.2.2>
    <s_s1_m1_m2_m3.2.2.2.2.2>
      <IFC>
  -2.578577152540298E-05  -3.035766082959412E-18  -4.607859233063394E-18
  -3.035766082959412E-18  -2.578577152540992E-05   2.168404344971009E-18
  -4.553649124439119E-18   2.222614453595284E-18  -2.578577152539691E-05
      </IFC>
    </s_s1_m1_m2_m3.2.2.2.2.2>
    <s_s1_m1_m2_m3.2.2.3.2.2>
      <IFC>
  -4.203739861953007E-04  -4.856894729035844E-04  -4.780808197830961E-04
  -3.519910384011424E-04  -3.163771518603625E-04   3.519910384011477E-04
  -4.780808197830961E-04   4.856894729035893E-04  -4.203739861952990E-04
      </IFC>
    </s_s1_m1_m2_m3.2.2.3.2.2>
    <s_s1_m1_m2_m3.2.2.4.2.2>
      <IFC>
  -4.094834901518327E-04  -3.469446951953614E-18  -1.951563910473908E-18
  -3.469446951953614E-18  -4.088760693871617E-04   4.391018798566293E-18
  -2.005774019098183E-18   4.336808689942018E-18  -4.094834901518353E-04
      </IFC>
    </s_s1_m1_m2_m3.2.2.4.2.2>
    <s_s1_m1_m2_m3.2.2.1.3.2>
      <IFC>
  -4.203739861953076E-04   4.780808197830974E-04  -4.856894729035903E-04
   4.780808197830974E-04  -4.203739861953007E-04  -4.856894729035854E-04
  -3.519910384011485E-04  -3.519910384011437E-04  -3.163771518603642E-04
      </IFC>
    </s_s1_m1_m2_m3.2.2.1.3.2>
    <s_s1_m1_m2_m3.2.2.2.3.2>
      <IFC>
  -3.163771518603763E-04  -3.519910384011446E-04  -3.519910384011449E-04
  -4.856894729035865E-04  -4.203739861953016E-04   4.780808197830961E-04
  -4.856894729035868E-04   4.780808197830960E-04  -4.203739861953042E-04
      </IFC>
    </s_s1_m1_m2_m3.2.2.2.3.2>
    <s_s1_m1_m2_m3.2.2.3.3.2>
      <IFC>
  -4.734657425754900E-04  -1.123187092262696E-04   7.341850851687478E-05
  -1.123187092262696E-04  -4.734657425754848E-04  -7.341850851688136E-05
  -7.341850851687835E-05   7.341850851687215E-05  -3.884019074319716E-04
      </IFC>
    </s_s1_m1_m2_m3.2.2.3.3.2>
    <s_s1_m1_m2_m3.2.2.4.3.2>
      <IFC>
  -3.884019074319664E-04   7.341850851687705E-05  -7.341850851688090E-05
  -7.341850851687597E-05  -4.734657425754839E-04  -1.123187092262639E-04
   7.341850851687212E-05  -1.123187092262638E-04  -4.734657425754744E-04
      </IFC>
    </s_s1_m1_m2_m3.2.2.4.3.2>
    <s_s1_m1_m2_m3.2.2.1.4.2>
      <IFC>
  -3.742641877241906E-03  -1.862497946339839E-03  -4.479053795943348E-03
   1.862497946339838E-03   1.059986195261797E-02   1.862497946339838E-03
  -4.479053795943348E-03  -1.862497946339839E-03  -3.742641877241906E-03
      </IFC>
    </s_s1_m1_m2_m3.2.2.1.4.2>
    <s_s1_m1_m2_m3.2.2.2.4.2>
      <IFC>
  -4.088760693871617E-04  -1.734723475976807E-18  -7.209944447028604E-18
  -1.734723475976807E-18  -4.094834901518362E-04  -1.301042606982605E-18
  -7.155734338404329E-18  -1.246832498358330E-18  -4.094834901518301E-04
      </IFC>
    </s_s1_m1_m2_m3.2.2.2.4.2>
    <s_s1_m1_m2_m3.2.2.3.4.2>
      <IFC>
  -4.734657425754830E-04  -7.341850851687472E-05   1.123187092262599E-04
   7.341850851687846E-05  -3.884019074319577E-04   7.341850851687597E-05
   1.123187092262599E-04  -7.341850851687749E-05  -4.734657425754778E-04
      </IFC>
    </s_s1_m1_m2_m3.2.2.3.4.2>
    <s_s1_m1_m2_m3.2.2.4.4.2>
      <IFC>
  -4.094834901518327E-04  -4.336808689942018E-19  -6.288372600415926E-18
  -4.336808689942018E-19  -4.094834901518362E-04   2.656295322589486E-18
  -6.342582709040201E-18   2.602085213965211E-18  -4.088760693871539E-04
      </IFC>
    </s_s1_m1_m2_m3.2.2.4.4.2>
    <s_s1_m1_m2_m3.2.2.1.1.3>
      <IFC>
  -2.939277549421360E-05   5.039471004495811E-04   5.421010862427522E-19
   5.039471004495811E-04  -2.939277549421360E-05  -1.029992063861229E-18
   5.421010862427522E-19  -1.029992063861229E-18   4.088223787532458E-03
      </IFC>
    </s_s1_m1_m2_m3.2.2.1.1.3>
    <s_s1_m1_m2_m3.2.2.2.1.3>
      <IFC>
  -4.203739861953085E-04   4.856894729035801E-04   4.780808197830970E-04
   3.519910384011382E-04  -3.163771518603781E-04   3.519910384011404E-04
   4.780808197830970E-04   4.856894729035822E-04  -4.203739861953102E-04
      </IFC>
    </s_s1_m1_m2_m3.2.2.2.1.3>
    <s_s1_m1_m2_m3.2.2.3.1.3>
      <IFC>
   4.088223787532456E-03  -4.607859233063394E-19   1.301042606982605E-18
  -4.607859233063394E-19  -2.939277549420492E-05   5.039471004495851E-04
   1.301042606982605E-18   5.039471004495851E-04  -2.939277549423441E-05
      </IFC>
    </s_s1_m1_m2_m3.2.2.3.1.3>
    <s_s1_m1_m2_m3.2.2.4.1.3>
      <IFC>
  -4.203739861953085E-04   3.519910384011382E-04   4.780808197830970E-04
   4.856894729035801E-04  -3.163771518603781E-04   4.856894729035822E-04
   4.780808197830970E-04   3.519910384011404E-04  -4.203739861953102E-04
      </IFC>
    </s_s1_m1_m2_m3.2.2.4.1.3>
    <s_s1_m1_m2_m3.2.2.1.2.3>
      <IFC>
  -3.163771518603677E-04   3.519910384011420E-04  -3.519910384011439E-04
   4.856894729035840E-04  -4.203739861953111E-04  -4.780808197830965E-04
  -4.856894729035861E-04  -4.780808197830965E-04  -4.203739861953042E-04
      </IFC>
    </s_s1_m1_m2_m3.2.2.1.2.3>
    <s_s1_m1_m2_m3.2.2.2.2.3>
      <IFC>
  -4.203739861953085E-04  -4.780808197830997E-04  -4.856894729035858E-04
  -4.780808197830997E-04  -4.203739861953068E-04   4.856894729035850E-04
  -3.519910384011438E-04   3.519910384011435E-04  -3.163771518603763E-04
      </IFC>
    </s_s1_m1_m2_m3.2.2.2.2.3>
    <s_s1_m1_m2_m3.2.2.3.2.3>
      <IFC>
  -3.884019074319577E-04  -7.341850851687819E-05  -7.341850851687990E-05
   7.341850851687494E-05  -4.734657425754917E-04   1.123187092262660E-04
   7.341850851687331E-05   1.123187092262660E-04  -4.734657425754726E-04
      </IFC>
    </s_s1_m1_m2_m3.2.2.3.2.3>
    <s_s1_m1_m2_m3.2.2.4.2.3>
      <IFC>
  -4.734657425754874E-04   1.123187092262647E-04   7.341850851687402E-05
   1.123187092262647E-04  -4.734657425754891E-04   7.341850851687770E-05
  -7.341850851687922E-05  -7.341850851687564E-05  -3.884019074319560E-04
      </IFC>
    </s_s1_m1_m2_m3.2.2.4.2.3>
    <s_s1_m1_m2_m3.2.2.1.3.3>
      <IFC>
  -2.939277549420666E-05   3.876022766635678E-18  -5.039471004495836E-04
   3.876022766635678E-18   4.088223787532444E-03  -2.710505431213761E-19
  -5.039471004495836E-04  -2.710505431213761E-19  -2.939277549422747E-05
      </IFC>
    </s_s1_m1_m2_m3.2.2.1.3.3>
    <s_s1_m1_m2_m3.2.2.2.3.3>
      <IFC>
  -4.734657425754874E-04   7.341850851687618E-05  -1.123187092262632E-04
  -7.341850851687684E-05  -3.884019074319681E-04   7.341850851688009E-05
  -1.123187092262634E-04  -7.341850851687337E-05  -4.734657425754856E-04
      </IFC>
    </s_s1_m1_m2_m3.2.2.2.3.3>
    <s_s1_m1_m2_m3.2.2.3.3.3>
      <IFC>
   3.355867178670060E-04   4.119968255444917E-18  -2.276824562219559E-18
   4.119968255444917E-18   3.355867178670095E-04   3.252606517456513E-19
  -2.276824562219559E-18   3.252606517456513E-19   3.355867178669938E-04
      </IFC>
    </s_s1_m1_m2_m3.2.2.3.3.3>
    <s_s1_m1_m2_m3.2.2.4.3.3>
      <IFC>
  -4.734657425754874E-04  -7.341850851687684E-05  -1.123187092262634E-04
   7.341850851687618E-05  -3.884019074319681E-04  -7.341850851687337E-05
  -1.123187092262632E-04   7.341850851688009E-05  -4.734657425754856E-04
      </IFC>
    </s_s1_m1_m2_m3.2.2.4.3.3>
    <s_s1_m1_m2_m3.2.2.1.4.3>
      <IFC>
  -3.163771518603677E-04   4.856894729035840E-04  -4.856894729035861E-04
   3.519910384011420E-04  -4.203739861953111E-04  -4.780808197830965E-04
  -3.519910384011439E-04  -4.780808197830965E-04  -4.203739861953042E-04
      </IFC>
    </s_s1_m1_m2_m3.2.2.1.4.3>
    <s_s1_m1_m2_m3.2.2.2.4.3>
      <IFC>
  -4.734657425754874E-04   1.123187092262647E-04  -7.341850851687922E-05
   1.123187092262647E-04  -4.734657425754891E-04  -7.341850851687564E-05
   7.341850851687402E-05   7.341850851687770E-05  -3.884019074319560E-04
      </IFC>
    </s_s1_m1_m2_m3.2.2.2.4.3>
    <s_s1_m1_m2_m3.2.2.3.4.3>
      <IFC>
  -3.884019074319577E-04   7.341850851687494E-05   7.341850851687331E-05
  -7.341850851687819E-05  -4.734657425754917E-04   1.123187092262660E-04
  -7.341850851687990E-05   1.123187092262660E-04  -4.734657425754726E-04
      </IFC>
    </s_s1_m1_m2_m3.2.2.3.4.3>
    <s_s1_m1_m2_m3.2.2.4.4.3>
      <IFC>
  -4.203739861953085E-04  -4.780808197830997E-04  -3.519910384011438E-04
  -4.780808197830997E-04  -4.203739861953068E-04   3.519910384011435E-04
  -4.856894729035858E-04   4.856894729035850E-04  -3.163771518603763E-04
      </IFC>
    </s_s1_m1_m2_m3.2.2.4.4.3>
    <s_s1_m1_m2_m3.2.2.1.1.4>
      <IFC>
  -3.742641877241909E-03   4.479053795943343E-03  -1.862497946339841E-03
   4.479053795943343E-03  -3.742641877241909E-03   1.862497946339840E-03
   1.862497946339836E-03  -1.862497946339837E-03   1.059986195261794E-02
      </IFC>
    </s_s1_m1_m2_m3.2.2.1.1.4>
    <s_s1_m1_m2_m3.2.2.2.1.4>
      <IFC>
   1.059986195261796E-02  -1.862497946339838E-03   1.862497946339837E-03
   1.862497946339839E-03  -3.742641877241906E-03   4.479053795943346E-03
  -1.862497946339840E-03   4.479053795943346E-03  -3.742641877241907E-03
      </IFC>
    </s_s1_m1_m2_m3.2.2.2.1.4>
    <s_s1_m1_m2_m3.2.2.3.1.4>
      <IFC>
  -4.203739861953076E-04   4.780808197831001E-04   3.519910384011388E-04
   4.780808197831001E-04  -4.203739861952990E-04   3.519910384011421E-04
   4.856894729035807E-04   4.856894729035839E-04  -3.163771518603694E-04
      </IFC>
    </s_s1_m1_m2_m3.2.2.3.1.4>
    <s_s1_m1_m2_m3.2.2.4.1.4>
      <IFC>
  -3.163771518603763E-04   4.856894729035836E-04   4.856894729035807E-04
   3.519910384011417E-04  -4.203739861953016E-04   4.780808197830952E-04
   3.519910384011388E-04   4.780808197830952E-04  -4.203739861953076E-04
      </IFC>
    </s_s1_m1_m2_m3.2.2.4.1.4>
    <s_s1_m1_m2_m3.2.2.1.2.4>
      <IFC>
  -3.742641877241906E-03   1.862497946339838E-03  -4.479053795943348E-03
  -1.862497946339839E-03   1.059986195261797E-02  -1.862497946339839E-03
  -4.479053795943348E-03   1.862497946339838E-03  -3.742641877241906E-03
      </IFC>
    </s_s1_m1_m2_m3.2.2.1.2.4>
    <s_s1_m1_m2_m3.2.2.2.2.4>
      <IFC>
  -4.094834901518327E-04  -4.336808689942018E-19  -6.342582709040201E-18
  -4.336808689942018E-19  -4.094834901518362E-04   2.602085213965211E-18
  -6.288372600415926E-18   2.656295322589486E-18  -4.088760693871539E-04
      </IFC>
    </s_s1_m1_m2_m3.2.2.2.2.4>
    <s_s1_m1_m2_m3.2.2.3.2.4>
      <IFC>
  -4.734657425754830E-04   7.341850851687846E-05   1.123187092262599E-04
  -7.341850851687472E-05  -3.884019074319577E-04  -7.341850851687749E-05
   1.123187092262599E-04   7.341850851687597E-05  -4.734657425754778E-04
      </IFC>
    </s_s1_m1_m2_m3.2.2.3.2.4>
    <s_s1_m1_m2_m3.2.2.4.2.4>
      <IFC>
  -4.088760693871617E-04  -1.734723475976807E-18  -7.155734338404329E-18
  -1.734723475976807E-18  -4.094834901518362E-04  -1.246832498358330E-18
  -7.209944447028604E-18  -1.301042606982605E-18  -4.094834901518301E-04
      </IFC>
    </s_s1_m1_m2_m3.2.2.4.2.4>
    <s_s1_m1_m2_m3.2.2.1.3.4>
      <IFC>
  -4.203739861953076E-04   4.780808197830974E-04  -3.519910384011485E-04
   4.780808197830974E-04  -4.203739861953007E-04  -3.519910384011437E-04
  -4.856894729035903E-04  -4.856894729035854E-04  -3.163771518603642E-04
      </IFC>
    </s_s1_m1_m2_m3.2.2.1.3.4>
    <s_s1_m1_m2_m3.2.2.2.3.4>
      <IFC>
  -3.884019074319664E-04  -7.341850851687597E-05   7.341850851687212E-05
   7.341850851687705E-05  -4.734657425754839E-04  -1.123187092262638E-04
  -7.341850851688090E-05  -1.123187092262639E-04  -4.734657425754744E-04
      </IFC>
    </s_s1_m1_m2_m3.2.2.2.3.4>
    <s_s1_m1_m2_m3.2.2.3.3.4>
      <IFC>
  -4.734657425754900E-04  -1.123187092262696E-04  -7.341850851687835E-05
  -1.123187092262696E-04  -4.734657425754848E-04   7.341850851687215E-05
   7.341850851687478E-05  -7.341850851688136E-05  -3.884019074319716E-04
      </IFC>
    </s_s1_m1_m2_m3.2.2.3.3.4>
    <s_s1_m1_m2_m3.2.2.4.3.4>
      <IFC>
  -3.163771518603763E-04  -4.856894729035865E-04  -4.856894729035868E-04
  -3.519910384011446E-04  -4.203739861953016E-04   4.780808197830960E-04
  -3.519910384011449E-04   4.780808197830961E-04  -4.203739861953042E-04
      </IFC>
    </s_s1_m1_m2_m3.2.2.4.3.4>
    <s_s1_m1_m2_m3.2.2.1.4.4>
      <IFC>
  -4.203739861953042E-04   3.519910384011446E-04  -4.780808197831013E-04
   4.856894729035866E-04  -3.163771518603677E-04  -4.856894729035841E-04
  -4.780808197831013E-04  -3.519910384011421E-04  -4.203739861953042E-04
      </IFC>
    </s_s1_m1_m2_m3.2.2.1.4.4>
    <s_s1_m1_m2_m3.2.2.2.4.4>
      <IFC>
  -4.094834901518327E-04  -3.469446951953614E-18  -2.005774019098183E-18
  -3.469446951953614E-18  -4.088760693871617E-04   4.336808689942018E-18
  -1.951563910473908E-18   4.391018798566293E-18  -4.094834901518353E-04
      </IFC>
    </s_s1_m1_m2_m3.2.2.2.4.4>
    <s_s1_m1_m2_m3.2.2.3.4.4>
      <IFC>
  -4.203739861953007E-04  -3.519910384011424E-04  -4.780808197830961E-04
  -4.856894729035844E-04  -3.163771518603625E-04   4.856894729035893E-04
  -4.780808197830961E-04   3.519910384011477E-04  -4.203739861952990E-04
      </IFC>
    </s_s1_m1_m2_m3.2.2.3.4.4>
    <s_s1_m1_m2_m3.2.2.4.4.4>
      <IFC>
  -2.578577152540298E-05  -3.035766082959412E-18  -4.553649124439119E-18
  -3.035766082959412E-18  -2.578577152540992E-05   2.222614453595284E-18
  -4.607859233063394E-18   2.168404344971009E-18  -2.578577152539691E-05
      </IFC>
    </s_s1_m1_m2_m3.2.2.4.4.4>
  </INTERATOMIC_FORCE_CONSTANTS>
</Root>
