<?xml version="1.0" encoding="UTF-8"?>
<Root>
  <GEOMETRY_INFO>
    <NUMBER_OF_TYPES>1</NUMBER_OF_TYPES>
    <NUMBER_OF_ATOMS>2</NUMBER_OF_ATOMS>
    <BRAVAIS_LATTICE_INDEX>2</BRAVAIS_LATTICE_INDEX>
    <SPIN_COMPONENTS>1</SPIN_COMPONENTS>
    <CELL_DIMENSIONS>
   1.035000000000000E+01   0.000000000000000E+00   0.000000000000000E+00
   0.000000000000000E+00   0.000000000000000E+00   0.000000000000000E+00
    </CELL_DIMENSIONS>
    <AT>
  -5.000000000000000E-01   0.000000000000000E+00   5.000000000000000E-01
   0.000000000000000E+00   5.000000000000000E-01   5.000000000000000E-01
  -5.000000000000000E-01   5.000000000000000E-01   0.000000000000000E+00
    </AT>
    <BG>
  -1.000000000000000E+00  -1.000000000000000E+00   1.000000000000000E+00
   1.000000000000000E+00   1.000000000000000E+00   1.000000000000000E+00
  -1.000000000000000E+00   1.000000000000000E+00  -1.000000000000000E+00
    </BG>
    <UNIT_CELL_VOLUME_AU>277.17946874999996</UNIT_CELL_VOLUME_AU>
    <TYPE_NAME.1>Si</TYPE_NAME.1>
    <MASS.1>28.085999999999999</MASS.1>
    <ATOM.1 SPECIES="Si" INDEX="1" TAU="0.0000000000000000 0.0000000000000000 0.0000000000000000"/>
    <ATOM.2 SPECIES="Si" INDEX="1" TAU="0.25000000000000000 0.25000000000000000 0.25000000000000000"/>
    <NUMBER_OF_Q>3</NUMBER_OF_Q>
  </GEOMETRY_INFO>
  <DIELECTRIC_PROPERTIES epsil="false" zstar="false" raman="false">
  </DIELECTRIC_PROPERTIES>
  <DYNAMICAL_MAT_.1>
    <Q_POINT>
   0.000000000000000E+00  -1.000000000000000E+00   0.000000000000000E+00
    </Q_POINT>
    <PHI.1.1>
   2.209276049025959E-01   0.000000000000000E+00
   0.000000000000000E+00   0.000000000000000E+00
   2.775557561562891E-17   0.000000000000000E+00
  -2.775557561562891E-17   0.000000000000000E+00
   3.296080380388799E-01   0.000000000000000E+00
  -2.775557561562891E-17   0.000000000000000E+00
   2.775557561562891E-17   0.000000000000000E+00
   2.775557561562891E-17   0.000000000000000E+00
   2.209276049025960E-01   0.000000000000000E+00
    </PHI.1.1>
    <PHI.1.2>
  -6.938893903907228E-18  -1.339953096592684E-33
   6.938893903907228E-18  -9.711628366719991E-34
  -1.632367431803778E-01   9.995367751954412E-18
   0.000000000000000E+00  -2.007908589171049E-34
   1.387778780781446E-17   9.711628366719991E-34
  -1.387778780781446E-17   1.339953096592684E-33
  -1.632367431803778E-01   9.995367751954414E-18
   6.938893903907228E-18   9.547671077152367E-34
  -6.938893903907228E-18  -1.725139085470131E-33
    </PHI.1.2>
    <PHI.2.1>
   0.000000000000000E+00  -2.007908589171049E-34
  -1.387778780781446E-17  -5.695811188377895E-34
  -1.632367431803778E-01  -9.995367751954411E-18
   6.938893903907228E-18  -5.695811188377895E-34
  -6.938893903907228E-18  -1.741534814426893E-33
   2.081668171172169E-17   9.711628366719991E-34
  -1.632367431803778E-01  -9.995367751954411E-18
  -6.938893903907228E-18   1.356348825549446E-33
  -2.081668171172169E-17  -1.356348825549446E-33
    </PHI.2.1>
    <PHI.2.2>
   2.209276049025959E-01   0.000000000000000E+00
   0.000000000000000E+00   0.000000000000000E+00
   2.775557561562891E-17   0.000000000000000E+00
  -2.775557561562891E-17   0.000000000000000E+00
   3.296080380388799E-01   0.000000000000000E+00
  -2.775557561562891E-17   0.000000000000000E+00
   2.775557561562891E-17   0.000000000000000E+00
   2.775557561562891E-17   0.000000000000000E+00
   2.209276049025960E-01   0.000000000000000E+00
    </PHI.2.2>
  </DYNAMICAL_MAT_.1>
  <DYNAMICAL_MAT_.2>
    <Q_POINT>
  -1.000000000000000E+00   0.000000000000000E+00   0.000000000000000E+00
    </Q_POINT>
    <PHI.1.1>
   3.296080380388801E-01   0.000000000000000E+00
   2.775557561562891E-17   0.000000000000000E+00
   0.000000000000000E+00   0.000000000000000E+00
  -2.775557561562891E-17   0.000000000000000E+00
   2.209276049025959E-01   0.000000000000000E+00
  -2.775557561562891E-17   0.000000000000000E+00
  -2.775557561562891E-17   0.000000000000000E+00
  -2.775557561562891E-17   0.000000000000000E+00
   2.209276049025959E-01   0.000000000000000E+00
    </PHI.1.1>
    <PHI.1.2>
  -6.938893903907228E-18   2.126720803304341E-33
  -6.938893903907228E-18   1.843951299603423E-34
   6.938893903907228E-18   5.859768477945521E-34
   0.000000000000000E+00   5.695811188377895E-34
   0.000000000000000E+00  -5.695811188377895E-34
  -1.632367431803778E-01   9.995367751954412E-18
  -1.387778780781446E-17   2.007908589171049E-34
  -1.632367431803778E-01   9.995367751954412E-18
   1.387778780781446E-17   2.007908589171049E-34
    </PHI.1.2>
    <PHI.2.1>
   1.387778780781446E-17  -1.741534814426893E-33
   0.000000000000000E+00  -1.339953096592684E-33
   1.387778780781446E-17   5.695811188377895E-34
   2.081668171172169E-17   5.859768477945521E-34
   6.938893903907228E-18   1.843951299603423E-34
  -1.632367431803778E-01  -9.995367751954412E-18
   2.081668171172169E-17  -2.007908589171049E-34
  -1.632367431803778E-01  -9.995367751954412E-18
   2.081668171172169E-17  -2.007908589171049E-34
    </PHI.2.1>
    <PHI.2.2>
   3.296080380388801E-01   0.000000000000000E+00
   2.775557561562891E-17   0.000000000000000E+00
   0.000000000000000E+00   0.000000000000000E+00
  -2.775557561562891E-17   0.000000000000000E+00
   2.209276049025959E-01   0.000000000000000E+00
  -2.775557561562891E-17   0.000000000000000E+00
  -2.775557561562891E-17   0.000000000000000E+00
  -2.775557561562891E-17   0.000000000000000E+00
   2.209276049025959E-01   0.000000000000000E+00
    </PHI.2.2>
  </DYNAMICAL_MAT_.2>
  <DYNAMICAL_MAT_.3>
    <Q_POINT>
   0.000000000000000E+00   0.000000000000000E+00  -1.000000000000000E+00
    </Q_POINT>
    <PHI.1.1>
   2.209276049025959E-01   0.000000000000000E+00
   1.387778780781446E-17   0.000000000000000E+00
  -1.387778780781446E-17   0.000000000000000E+00
   1.387778780781446E-17   0.000000000000000E+00
   2.209276049025960E-01   0.000000000000000E+00
   1.387778780781446E-17   0.000000000000000E+00
   1.387778780781446E-17   0.000000000000000E+00
   1.387778780781446E-17   0.000000000000000E+00
   3.296080380388801E-01   0.000000000000000E+00
    </PHI.1.1>
    <PHI.1.2>
   0.000000000000000E+00   0.000000000000000E+00
  -1.632367431803778E-01   9.995367751954412E-18
   0.000000000000000E+00   0.000000000000000E+00
  -1.632367431803778E-01   9.995367751954411E-18
   0.000000000000000E+00  -1.540743955509789E-33
   0.000000000000000E+00   0.000000000000000E+00
   0.000000000000000E+00   0.000000000000000E+00
   2.775557561562891E-17   0.000000000000000E+00
   0.000000000000000E+00   1.540743955509789E-33
    </PHI.1.2>
    <PHI.2.1>
   0.000000000000000E+00   0.000000000000000E+00
  -1.632367431803778E-01  -9.995367751954412E-18
   0.000000000000000E+00   0.000000000000000E+00
  -1.632367431803778E-01  -9.995367751954412E-18
   0.000000000000000E+00   0.000000000000000E+00
   0.000000000000000E+00   0.000000000000000E+00
   1.387778780781446E-17   0.000000000000000E+00
   1.387778780781446E-17   0.000000000000000E+00
  -1.387778780781446E-17  -1.540743955509789E-33
    </PHI.2.1>
    <PHI.2.2>
   2.209276049025959E-01   0.000000000000000E+00
   1.387778780781446E-17   0.000000000000000E+00
  -1.387778780781446E-17   0.000000000000000E+00
   1.387778780781446E-17   0.000000000000000E+00
   2.209276049025960E-01   0.000000000000000E+00
   1.387778780781446E-17   0.000000000000000E+00
   1.387778780781446E-17   0.000000000000000E+00
   1.387778780781446E-17   0.000000000000000E+00
   3.296080380388801E-01   0.000000000000000E+00
    </PHI.2.2>
  </DYNAMICAL_MAT_.3>
  <FREQUENCIES_THZ_CMM1>
    <OMEGA.1>
   4.938767137256445E+00   1.647395391533314E+02
    </OMEGA.1>
    <DISPLACEMENT.1>
  0.56621425697192684       -0.0000000000000000     
   4.2625695170839046E-017  -0.0000000000000000     
 -0.42355804230557204        0.0000000000000000     
 -0.42355804230557231        0.0000000000000000     
  -1.0414848873750607E-016   0.0000000000000000     
  0.56621425697192662       -0.0000000000000000     
    </DISPLACEMENT.1>
    <OMEGA.2>
   4.938767137256451E+00   1.647395391533316E+02
    </OMEGA.2>
    <DISPLACEMENT.2>
 -0.42355804230557231        0.0000000000000000     
  -3.7860885794861950E-017   0.0000000000000000     
 -0.56621425697192684        0.0000000000000000     
 -0.56621425697192684        0.0000000000000000     
   3.5822398111508808E-016   0.0000000000000000     
 -0.42355804230557209        0.0000000000000000     
    </DISPLACEMENT.2>
    <OMEGA.3>
   1.180494406825001E+01   3.937705486990607E+02
    </OMEGA.3>
    <DISPLACEMENT.3>
   1.7983799296109972E-016   0.0000000000000000     
 -0.84093127843046522        0.0000000000000000     
   3.5670116570411727E-016   0.0000000000000000     
  -4.3612391700292140E-016   0.0000000000000000     
 -0.54114192681523332        0.0000000000000000     
  -2.4345942341686835E-016   0.0000000000000000     
    </DISPLACEMENT.3>
    <OMEGA.4>
   1.180494406825001E+01   3.937705486990608E+02
    </OMEGA.4>
    <DISPLACEMENT.4>
   3.3937822553948987E-016   0.0000000000000000     
  0.54114192681523343        0.0000000000000000     
  -4.3857557557864888E-016   0.0000000000000000     
   4.6420652222144457E-016   0.0000000000000000     
 -0.84093127843046511        0.0000000000000000     
  -5.5264311312303798E-016   0.0000000000000000     
    </DISPLACEMENT.4>
    <OMEGA.5>
   1.274452242376915E+01   4.251115091017116E+02
    </OMEGA.5>
    <DISPLACEMENT.5>
 -0.38353140965670024        0.0000000000000000     
   8.8879391045565974E-016   0.0000000000000000     
  0.59405694828588973        0.0000000000000000     
 -0.59405694828588973        0.0000000000000000     
  -7.1167008890573018E-016   0.0000000000000000     
  0.38353140965670030        0.0000000000000000     
    </DISPLACEMENT.5>
    <OMEGA.6>
   1.274452242376915E+01   4.251115091017116E+02
    </OMEGA.6>
    <DISPLACEMENT.6>
 -0.59405694828588973        0.0000000000000000     
  -4.8265780963979076E-016   0.0000000000000000     
 -0.38353140965670030        0.0000000000000000     
  0.38353140965670024        0.0000000000000000     
  -1.8993825714396533E-016   0.0000000000000000     
  0.59405694828588995        0.0000000000000000     
    </DISPLACEMENT.6>
  </FREQUENCIES_THZ_CMM1>
</Root>
